Workbook

Sheet JESTH- 2083
A1: Product Name | B1: Bucket Size | C1: SALES | D1: MP
A2: ACE AC1/6 | B2: 1 | C2: 450 | D2: 598
A3: ACE AC1/6 | B3: 4 | C3: 1600 | D3: 2151
A4: ACE AC1/6 | B4: 10 | C4: 3800 | D4: 4962
A5: ACE AC1/6 | B5: 20 | C5: 7000 | D5: 9570
A6: ACE AC10 | B6: 0.975
A7: ACE AC10 | B7: 3.9
A8: ACE AC10 | B8: 9.75
A9: ACE AC10 | B9: 19.5
A10: ACE AC17/18 | B10: 0.925
A11: ACE AC17/18 | B11: 3.7
A12: ACE AC17/18 | B12: 9.25
A13: ACE AC17/18 | B13: 18.5
A14: ACE AC13/15/20 | B14: 0.975
A15: ACE AC13/15/20 | B15: 3.9
A16: ACE AC13/15/20 | B16: 9.75
A17: ACE AC13/15/20 | B17: 19.5
A19: APEX AB2/6 | B19: 1 | C19: 800 | D19: 1107
A20: APEX AB2/6 | B20: 4 | C20: 3000 | D20: 4215
A21: APEX AB2/6 | B21: 10 | C21: 6800 | D21: 9919
A22: APEX AB2/6 | B22: 20 | C22: 13500 | D22: 19517
A23: APEX AB10/17/18 | B23: 0.975
A24: APEX AB10/17/18 | B24: 3.9
A25: APEX AB10/17/18 | B25: 9.75
A26: APEX AB10/17/18 | B26: 19.5
A27: APEX AB13/15/20 | B27: 0.975
A28: APEX AB13/15/20 | B28: 3.9
A29: APEX AB13/15/20 | B29: 9.75
A30: APEX AB13/15/20 | B30: 19.5
A32: APEX ULTIMA HQ2/6 | B32: 1 | C32: 900 | D32: 1358
A33: APEX ULTIMA HQ2/6 | B33: 4 | C33: 3400 | D33: 5229
A34: APEX ULTIMA HQ2/6 | B34: 10 | C34: 8250 | D34: 12474
A35: APEX ULTIMA HQ2/6 | B35: 20 | C35: 16000 | D35: 24532
A36: APEX ULTIMA HQ10 | B36: 0.975
A37: APEX ULTIMA HQ10 | B37: 3.9
A38: APEX ULTIMA HQ10 | B38: 9.75
A39: APEX ULTIMA HQ10 | B39: 19.5
A40: APEX ULTIMA HQ13 | B40: 0.975
A41: APEX ULTIMA HQ13 | B41: 3.9
A42: APEX ULTIMA HQ13 | B42: 9.75
A43: APEX ULTIMA HQ13 | B43: 19.5
A44: APEX ULTIMA HQ15 | B44: 0.975
A45: APEX ULTIMA HQ15 | B45: 3.9
A46: APEX ULTIMA HQ15 | B46: 9.75
A47: APEX ULTIMA HQ15 | B47: 19.5
... A55: APEX ULTIMA HQ20 | B55: 19
A57: ULTIMA BASECOAT | B57: 1 | D57: 590
A58: ULTIMA BASECOAT | B58: 4 | D58: 2170
A59: ULTIMA BASECOAT | B59: 10 | D59: 4999
A60: ULTIMA BASECOAT | B60: 20 | D60: 9790
A62: ULTIMA PROTEK UP1/16/17 | B62: 1 | D62: 1707
A63: ULTIMA PROTEK UP1 | B63: 4 | D63: 6570
A64: ULTIMA PROTEK UP1 | B64: 10 | D64: 15778
A65: ULTIMA PROTEK UP1 | B65: 20 | D65: 30995
A66: ULTIMA PROTEK UP10 | B66: 1
A67: ULTIMA PROTEK UP10 | B67: 4
A68: ULTIMA PROTEK UP10 | B68: 10
A69: ULTIMA PROTEK UP10 | B69: 20
A70: ULTIMA PROTEK UP20/13 | B70: 1
A71: ULTIMA PROTEK UP20/13 | B71: 4
A72: ULTIMA PROTEK UP20/13 | B72: 10
A73: ULTIMA PROTEK UP20/13 | B73: 20
A75: ULTIMA PROTEK PS1 | B75: 1 | C75: 1300 | D75: 1792
A76: ULTIMA PROTEK PS1 | B76: 4 | C76: 4800 | D76: 6899
A77: ULTIMA PROTEK PS1 | B77: 10 | C77: 11500 | D77: 16567
A78: ULTIMA PROTEK PS1 | B78: 20 | C78: 21500 | D78: 32545
A79: ULTIMA PROTEK PS10 | B79: 0.975
A80: ULTIMA PROTEK PS10 | B80: 3.9
A81: ULTIMA PROTEK PS10 | B81: 9.75
A82: ULTIMA PROTEK PS10 | B82: 19.5
A83: ULTIMA PROTEK PS13/15/20 | B83: 0.975
A84: ULTIMA PROTEK PS13/15/20 | B84: 3.9
A85: ULTIMA PROTEK PS13/15/20 | B85: 9.75
A86: ULTIMA PROTEK PS13/15/20 | B86: 19.5
A88: ULTIMA CLEAR | B88: 1 | C88: 1100 | D88: 1358
A89: ULTIMA CLEAR | B89: 4 | C89: 4500 | D89: 5229
A90: ULTIMA CLEAR | B90: 10 | C90: 10500 | D90: 12474
A91: ULTIMA CLEAR | B91: 20 | C91: 20700 | D91: 24532
A93: DAMP DEFENSE DD01 | B93: 1 | C93: 1100 | D93: 1755
A94: DAMP DEFENSE DD01 | B94: 4 | C94: 4000 | D94: 6804
A95: DAMP DEFENSE DD01 | B95: 10 | C95: 9500 | D95: 16524
A96: DAMP DEFENSE DD01 | B96: 20 | C96: 18000 | D96: 32076
A97: DAMP DEFENSE DD10 | B97: 0.975
A98: DAMP DEFENSE DD10 | B98: 3.9
A99: DAMP DEFENSE DD10 | B99: 9.75
A100: DAMP DEFENSE DD10 | B100: 19.5
A101: DAMP DEFENSE DD20 | B101: 0.95
A102: DAMP DEFENSE DD20 | B102: 3.8
A103: DAMP DEFENSE DD20 | B103: 9.5
A104: DAMP DEFENSE DD20 | B104: 19
A106: TRACTOR TE1/6 | B106: 1 | C106: 400 | D106: 547
A107: TRACTOR TE1/6 | B107: 4 | C107: 1400 | D107: 1891
A108: TRACTOR TE1/6 | B108: 10 | C108: 3200 | D108: 4513
A109: TRACTOR TE1/6 | B109: 20 | C109: 6000 | D109: 8689
A110: TRACTOR TE13/15 | B110: 0.9
A111: TRACTOR TE13/15 | B111: 3.6
A112: TRACTOR TE13/15 | B112: 9
A113: TRACTOR TE13/15 | B113: 18
A114: TRACTOR TE22 | B114: 0.95
A115: TRACTOR TE22 | B115: 3.8
...

Sheet Sheet125
C1: Dinesh shrestha
A2: Date | B2: Site | C2: DR Amount | D2: CR Amount | E2: Balance Amount
A3: 66421 | B3: suncity | C3: 235755 | E3: 235755
A4: 66422 | B4: suncity | C4: 253000 | E4: 488755
A5: 66427 | B5: cheque | D5: 488755 | E5: 0
A6: 66427 | B6: suncity | C6: 253000 | E6: 253000
A7: 66428 | B7: suncity | C7: 128400 | E7: 381400
A8: 66428 | B8: suncity | C8: 78450 | E8: 459850
A9: 66430 | B9: cheque | D9: 539850 | E9: -80000
A10: 66431 | B10: cash return | C10: 80000 | E10: 0
A11: 66433 | B11: suncity | C11: 38800 | E11: 38800
A12: 66433 | B12: suncity | C12: 372305 | E12: 411105
A13: 66438 | B13: cheque | D13: 411000 | E13: 105
A14: 66438 | B14: discount | D14: 105 | E14: 0
A15: 66438 | B15: suncity | C15: 126500 | E15: 126500
A16: 66440 | B16: suncity | C16: 253000 | E16: 379500
A17: 66442 | B17: suncity | C17: 252605 | E17: 632105
A18: 66443 | B18: suncity | C18: 415750 | E18: 1047855
A19: 66443 | B19: kharipati | C19: 179637 | E19: 1227492
A20: 66446 | B20: suncity | C20: 38700 | E20: 1266192
A21: 66447 | B21: cheque | D21: 404760 | E21: 861432
A22: 66449 | B22: cheque return | C22: 404760 | E22: 1266192
A23: 66449 | B23: kharipati | C23: 11500 | E23: 1277692

Sheet Sheet126
Y1: biswasilo consturction | Z1: 9849655774
Y2: w/p | Z2: 2+2
Y3: dcpm | Z3: 4+60+420+80+2+20+40+12+20
Y4: wall putty | Z4: 240+800+240+80+600+200+40
Y5: Damp proof | Z5: 60+80+40+20+20
Y6: te | Z6: 10+20+1+4+81+34+10
Y7: pge | Z7: 4+5+1+1+3+4+5+1+2+4+2+4+2+44
Y8: ta | Z8: 21+4+2
Y9: hq | Z9: 21+30+4+3+30+2+6+14
Y10: ext primer | Z10: 40+20+20
Y11: RB | Z11: 10+41+1+20+48+20
Y12: BW | Z12: 1+20
Y13: neo | Z13: 40+20+20
Y14: PS | Z14: 10

Sheet Sheet124

Sheet Sheet3

Sheet Sheet1
B1: ` | C1: SALES | D1: EXTERIOR PRIMER | E1: 1 | F1: 350
A2: ACE AC1/6/10/17/18 | B2: 1 | C2: 450 | D2: EXTERIOR PRIMER | E2: 4 | F2: 1200
A3: ACE AC1/6/10/17/18 | B3: 4 | C3: 1600 | D3: EXTERIOR PRIMER | E3: 10 | F3: 2900
A4: ACE AC1/6/10/17/18 | B4: 10 | C4: 3400 | D4: EXTERIOR PRIMER | E4: 20 | F4: 5500
A5: ACE AC1/6/10/17/18 | B5: 20 | C5: 6600
D6: DCP PRIMER(M) | E6: 1 | F6: 300
A7: APEX AB2/6/10/17/18 | B7: 1 | C7: 700 | D7: DCP PRIMER(M) | E7: 4 | F7: 1000
A8: APEX AB2/6/10/17/18 | B8: 4 | C8: 2700 | D8: DCP PRIMER(M) | E8: 10 | F8: 2050
A9: APEX AB2/6/10/17/18 | B9: 10 | C9: 6250 | D9: DCP PRIMER(M) | E9: 20 | F9: 3800
A10: APEX AB2/6/10/17/18 | B10: 20 | C10: 12000
A12: APEX ULTIMA HQ2/6/16/17 | B12: 1 | C12: 850 | D12: ASIAN WOOD PRIMER W/P | E12: 0.5 | F12: 285
A13: APEX ULTIMA HQ2/6/16/17 | B13: 4 | C13: 3200 | D13: ASIAN WOOD PRIMER W/P | E13: 1 | F13: 525
A14: APEX ULTIMA HQ2/6/16/17 | B14: 10 | C14: 7500 | D14: ASIAN WOOD PRIMER W/P | E14: 4 | F14: 1900
A15: APEX ULTIMA HQ2/6/16/17 | B15: 20 | C15: 14500
D16: ASIAN METAL PRIMER M/P | E16: 0.5 | F16: 250
A17: ULTIMA BASECOAT | B17: 1 | D17: ASIAN METAL PRIMER M/P | E17: 1 | F17: 450
A18: ULTIMA BASECOAT | B18: 4 | D18: ASIAN METAL PRIMER M/P | E18: 4 | F18: 1650
A19: ULTIMA BASECOAT | B19: 10 | D19: ASIAN METAL PRIMER M/P | E19: 20 | F19: 7500
A20: ULTIMA BASECOAT | B20: 20
D21: PGE BLAZZING WHITE | E21: 0.5 | F21: 400
A22: ULTIMA PROTEK PS1 | B22: 1 | C22: 1200 | D22: PGE BLAZZING WHITE | E22: 1 | F22: 750
A23: ULTIMA PROTEK PS1 | B23: 4 | C23: 4700 | D23: PGE BLAZZING WHITE | E23: 4 | F23: 2900
A24: ULTIMA PROTEK PS1 | B24: 10 | C24: 11000
A25: ULTIMA PROTEK PS1 | B25: 20 | C25: 21500 | D25: PGE GRI (Brown black some grey) | E25: 0.5 | F25: 375
D26: PGE GRI | E26: 1 | F26: 675
A27: ULTIMA CLEAR | B27: 1 | C27: 1100
A28: ULTIMA CLEAR | B28: 4 | C28: 4500 | D28: PGE GRII (gol yellow sing red bus green) | E28: 0.5 | F28: 400
A29: ULTIMA CLEAR | B29: 10 | C29: 10500 | D29: PGE GRII | E29: 1 | F29: 750
A30: ULTIMA CLEAR | B30: 20 | C30: 20700
D31: PGE EB1 | E31: 1 | F31: 700
A32: DAMP DEFENSE DD01 | B32: 1 | C32: 1300 | D32: PGE EB1 | E32: 4 | F32: 2700
A33: DAMP DEFENSE DD01 | B33: 4 | C33: 5000
A34: DAMP DEFENSE DD01 | B34: 10 | C34: 12000
A35: DAMP DEFENSE DD01 | B35: 20 | C35: 23500 | D35: Satin Enamel SE2 | E35: 1 | F35: 1000
D36: Satin Enamel SE2 | E36: 4 | F36: 3900
A37: TRACTOR TE1/6 | B37: 1 | C37: 350 | D37: SATIN ALL SHADES | E37: 1 | F37: 1100
A38: TRACTOR TE1/6 | B38: 4 | C38: 1200 | D38: SATIN ALL SHADES | E38: 4 | F38: 4200
A39: TRACTOR TE1/6 | B39: 10 | C39: 2900
A40: TRACTOR TE1/6 | B40: 20 | C40: 5500 | D40: Damp Proof | E40: 4 | F40: 3100
D41: Damp Proof | E41: 10 | F41: 7600
A42: TRACTOR EMULSION ADVANCED TA1/6 | B42: 1 | C42: 450 | D42: Damp Proof | E42: 20 | F42: 15000
A43: TRACTOR EMULSION ADVANCED TA1/6 | B43: 4 | C43: 1500
A44: TRACTOR EMULSION ADVANCED TA1/6 | B44: 10 | C44: 3600 | D44: Damp Block 2k | E44: 3 | F44: 1100
A45: TRACTOR EMULSION ADVANCED TA1/6 | B45: 20 | C45: 7500 | D45: Damp Block 2k | E45: 15 | F45: 5200
A47: PREMIUM BW1/6 | B47: 1 | C47: 600 | D47: VITALIA | E47: 1 | F47: 325
A48: PREMIUM BW1/6 | B48: 4 | C48: 2200 | D48: VITALIA NEO | E48: 1 | F48: 250
A49: PREMIUM BW1/6 | B49: 10 | C49: 5300 | D49: VITALIA NEO | E49: 5 | F49: 1050
A50: PREMIUM BW1/6 | B50: 20 | C50: 10300 | D50: VITALIA NEO | E50: 10 | F50: 1700
D51: VITALIA NEO | E51: 20 | F51: 33OO
A52: ROYAL RB1/6 | B52: 1 | C52: 800
A53: ROYAL RB1/6 | B53: 4 | C53: 3100 | D53: REPAIRE POLYMER | E53: 0.25 | F53: 150
A54: ROYAL RB1/6 | B54: 10 | C54: 7600 | D54: REPAIRE POLYMER | E54: 1 | F54: 600
A55: ROYAL RB1/6 | B55: 20 | C55: 15000
D56: Clear Varnish | E56: 0.5 | F56: 290
A57: Shyne SN2/7 | B57: 1 | C57: 1200 | D57: Clear Varnish | E57: 1 | F57: 550
A58: Shyne SN2/7 | B58: 4 | C58: 4600 | D58: Clear Varnish | E58: 4 | F58: 2000
A59: Shyne SN2/7 | B59: 10 | C59: 11000
A60: Shyne SN2/7 | B60: 20 | C60: 21000 | D60: TOUCH WOOD | E60: 0.5 | F60: 375
D61: TOUCH WOOD | E61: 1 | F61: 700
A62: ASPIRA AR2 | B62: 1 | C62: 1350 | D62: TOUCH WOOD | E62: 4 | F62: 2600
A63: Aspira AR2 | B63: 4 | C63: 5200
D64: 3 MANGO ALUMINIUM | E64: 0.2 | F64: 250
A65: ROYAL HEALTH SHILED HS2 | B65: 1 | C65: 1550 | D65: 3 MANGO ALUMINIUM | E65: 0.5 | F65: 450
A66: ROYAL HEALTH SHILED HS2 | B66: 4 | C66: 5900 | D66: 3 MANGO ALUMINIUM | E66: 1 | F66: 850
A67: ROYAL HEALTH SHILED HS2 | B67: 10 | C67: 14200
A68: ROYAL HEALTH SHILED HS2 | B68: 20 | C68: 28200 | D68: ROYAL PLAY PG5 | E68: 0.2 | F68: 350
D69: ROYAL PLAY PG5 | E69: 1 | F69: 1425
A70: ROYAL BLING BL1 | B70: 1 | C70: 1200 | D70: ROYAL PLAY METALIC GOLD | E70: 0.2 | F70: 600
A71: ROYAL BLING BL1 | B71: 4 | C71: 4500 | D71: ROYAL PLAY METALIC GOLD | E71: 1 | F71: 2670
A72: ROYAL BLING BL1 | B72: 10 | C72: 10700 | D72: ROYAL PLAY METALIC COPPER | E72: 0.2 | F72: 600
A73: ROYAL BLING BL1 | B73: 20 | C73: 20500 | D73: ROYAL PLAY METALIC COPPER | E73: 1 | F73: 2670
D74: ROYAL PLAY METALIC SILVER | E74: 0.2 | F74: 600
A75: TRACTOR AD1/6 | B75: 1 | C75: 260 | D75: ROYAL PLAY METALIC SILVER | E75: 1 | F75: 2670
A76: TRACTOR AD1/6 | B76: 5 | C76: 1100
A77: TRACTOR AD1/6 | B77: 10 | C77: 2100 | D77: ULTIMA METALIC GOLD | E77: 0.2 | F77: 725
A78: TRACTOR AD1/6 | B78: 20 | C78: 3900 | D78: ULTIMA METALIC GOLD | E78: 1 | F78: 2850
D79: ULTIMA METALIC SILVER | E79: 0.2 | F79: 650
A80: UTSAV UD1 TRACTOR UNO | B80: 1 | C80: 150 | D80: ULTIMA METALIC SILVER | E80: 1 | F80: 2400
A81: UTSAV UD1 TRACTOR UNO | B81: 5 | C81: 600
A82: UTSAV UD1 TRACTOR UNO | B82: 10 | C82: 1100 | D82: HYDROLOC | E82: 1 | F82: 1300
A83: UTSAV UD1 TRACTOR UNO | B83: 20 | C83: 2000 | D83: HYDROLOC | E83: 4 | F83: 5000
D84: HYDROLOC | E84: 10
D85: HYDROLOC | E85: 20
D87: SILICON SHIELD | E87: 1 | F87: 1450
D88: SILICON SHIELD | E88: 4 | F88: 5250

Sheet Sheeppt1
G5: `
B12: NAME | C12: SIZE | D12: sales | E12: Full Rate | G12: Name | H12: SIZE | I12: SALES | J12: Full Rate
B13: Interior | G13: Exterior
B14: UNO Distemper | C14: 1 | D14: ='JESTH- 2083'!C228 -> 175 | E14: ='JESTH- 2083'!D228 -> 223 | G14: ACE | H14: 1 | I14: ='JESTH- 2083'!C2 -> 450 | J14: ='JESTH- 2083'!D2 -> 598
B15: UNO Distemper | C15: 20 | D15: ='JESTH- 2083'!C231 -> 2200 | E15: ='JESTH- 2083'!D231 -> 3307 | G15: ACE | H15: 20 | I15: ='JESTH- 2083'!C5 -> 7000 | J15: ='JESTH- 2083'!D5 -> 9570
B17: TRACTOR Distemper | C17: 1 | D17: ='JESTH- 2083'!C219 -> 260 | E17: ='JESTH- 2083'!D219 -> 317 | G17: APEX | H17: 1 | I17: ='JESTH- 2083'!C19 -> 800 | J17: ='JESTH- 2083'!D19 -> 1107
B18: TRACTOR Distemper | C18: 20 | D18: ='JESTH- 2083'!C222 -> 3900 | E18: ='JESTH- 2083'!D222 -> 4964 | G18: APEX | H18: 20 | I18: ='JESTH- 2083'!C22 -> 13500 | J18: ='JESTH- 2083'!D22 -> 19517
B20: TRACTOR Emulsion | C20: 1 | D20: ='JESTH- 2083'!C106 -> 400 | E20: ='JESTH- 2083'!D106 -> 547 | G20: APEX ULTIMA 7Yrs | H20: 1 | I20: ='JESTH- 2083'!C32 -> 900 | J20: ='JESTH- 2083'!D32 -> 1358
B21: TRACTOR Emulsion | C21: 20 | D21: ='JESTH- 2083'!C109 -> 6000 | E21: ='JESTH- 2083'!D109 -> 8689 | G21: APEX ULTIMA 7Yrs | H21: 20 | I21: ='JESTH- 2083'!C35 -> 16000 | J21: ='JESTH- 2083'!D35 -> 24532
B23: PREMIUM Emulsion | C23: 1 | D23: ='JESTH- 2083'!C132 -> 700 | E23: ='JESTH- 2083'!D132 -> 892
B24: PREMIUM Emulsion | C24: 20 | D24: ='JESTH- 2083'!C135 -> 11500 | E24: ='JESTH- 2083'!D135 -> 15705
B26: ROYAL Emulsion | C26: 1 | D26: ='JESTH- 2083'!C149 -> 900 | E26: ='JESTH- 2083'!D149 -> 1391 | G26: ULTIMA PROTEK SHYNE 10Yrs | H26: 1 | I26: ='JESTH- 2083'!C75 -> 1300 | J26: ='JESTH- 2083'!D75 -> 1792
B27: ROYAL Emulsion | C27: 20 | D27: ='JESTH- 2083'!C152 -> 16000 | E27: ='JESTH- 2083'!D152 -> 25227 | G27: ULTIMA PROTEK SHYNE 10Yrs | H27: 20 | I27: ='JESTH- 2083'!C78 -> 21500 | J27: ='JESTH- 2083'!D78 -> 32545
B29: ROYAL Shyne Emulsion | C29: 1 | D29: ='JESTH- 2083'!C166 -> 1200 | E29: ='JESTH- 2083'!D166 -> 1744 | G29: DAMP DEFENSE (Weather Coat)6Yrs | H29: 1 | I29: ='JESTH- 2083'!C93 -> 1100 | J29: ='JESTH- 2083'!D93 -> 1755
B30: ROYAL Shyne Emulsion | C30: 20 | D30: ='JESTH- 2083'!C169 -> 21000 | E30: ='JESTH- 2083'!D169 -> 31693 | G30: DAMP DEFENSE (Weather Coat)6Yrs | H30: 20 | I30: ='JESTH- 2083'!C96 -> 18000 | J30: ='JESTH- 2083'!D96 -> 32076
B32: ROYALE BASE COAT | C32: 1 | D32: ='JESTH- 2083'!C179 -> 550 | E32: ='JESTH- 2083'!D179 -> 560 | G32: Primer
B33: ROYALE BASE COAT | C33: 20 | D33: ='JESTH- 2083'!C182 -> 8000 | E33: ='JESTH- 2083'!D182 -> 8370 | G33: DCP PRIMER(M) INT. | H33: 1 | I33: ='JESTH- 2083'!C238 -> 325 | J33: ='JESTH- 2083'!D238 -> 403
G34: DCP PRIMER(M) INT. | H34: 20 | I34: ='JESTH- 2083'!C241 -> 4000 | J34: ='JESTH- 2083'!D241 -> 5999
B35: ROYAL BILING 10 yrs | C35: 1 | D35: ='JESTH- 2083'!C206 -> 1400 | E35: ='JESTH- 2083'!D206 -> 2140
B36: ROYAL BILING 10 yrs | C36: 20 | D36: ='JESTH- 2083'!C209 -> 24500 | E36: ='JESTH- 2083'!D209 -> 36594 | G36: EXTERIOR PRIMER | H36: 1 | I36: ='JESTH- 2083'!C233 -> 375 | J36: ='JESTH- 2083'!D233 -> 562
G37: EXTERIOR PRIMER | H37: 20 | I37: ='JESTH- 2083'!C236 -> 5500 | J37: ='JESTH- 2083'!D236 -> 8882
B38: ROYAL HEALTH SHILED | C38: 1 | D38: ='JESTH- 2083'!C193 -> 1550 | E38: ='JESTH- 2083'!D193 -> 2140
B39: ROYAL HEALTH SHILED | C39: 20 | D39: ='JESTH- 2083'!C196 -> 28200 | E39: ='JESTH- 2083'!D196 -> 36594 | G39: WALL PUTTY | H39: 40 | I39: ='JESTH- 2083'!C326 -> 1400 | J39: ='JESTH- 2083'!D326 -> 2642
G41: Damp Proof 8Yrs | H41: 20 | I41: ='JESTH- 2083'!C340 -> 15500 | J41: ='JESTH- 2083'!D340 -> 19895
B42: Enamel | G42: Damp Proof SPARK 3Yrs | H42: 20 | I42: ='JESTH- 2083'!C335 -> 11500 | J42: ='JESTH- 2083'!D335 -> 11615
B43: PGE BLAZZING WHITE | C43: 1 | D43: ='JESTH- 2083'!C275 -> 850 | E43: ='JESTH- 2083'!D275 -> 1092 | G43: Damp Proof ULTRA 10Yrs | H43: 20 | I43: ='JESTH- 2083'!C343 -> 19000 | J43: ='JESTH- 2083'!D343 -> 23256
B44: PGE BLAZZING WHITE | C44: 4 | D44: ='JESTH- 2083'!C276 -> 3200 | E44: ='JESTH- 2083'!D276 -> 4229
G45: Enamel
B46: PGE GRI | C46: 1 | D46: ='JESTH- 2083'!C280 -> 800 | E46: ='JESTH- 2083'!D279 -> 513 | G46: PGE GRII | H46: 1 | I46: ='JESTH- 2083'!C285 -> 875 | J46: ='JESTH- 2083'!D285 -> 1079
B47: PGE GRI | C47: 4 | D47: ='JESTH- 2083'!C281 -> 3000 | E47: ='JESTH- 2083'!D281 -> 3752 | G47: PGE GRII | H47: 4 | I47: ='JESTH- 2083'!C286 -> 3300 | J47: ='JESTH- 2083'!D286 -> 4102
B51: ( + COLOUR CHARGE )

Sheet Sheet127
A1: target | B1: till date | C1: remeaning | D1: enamel | E1: wpcc | F1: prelux | G1: economy
A2: 75 | B2: 17 | C2: =A2-B2 -> 58 | D2: 0.15 | E2: 0.2 | F2: 0.4 | G2: 0.25
D3: 5 | E3: 10 | F3: 30 | G3: 13
A4: 10000 | D4: 5000 | E4: 8000 | F4: 40000 | G4: 7000 | H4: 35000
A6: collection | B6: 20lakh
A7: pdc | B7: 70.75
O13: =248+70 -> 318
L16: =248+105 -> 353
P21: =450-L16 -> 97
P25: =75*1.21 -> 90.75
Q26: =P25-30 -> 60.75

Sheet misc
B1: Size | C1: LANDING | D1: SALES Rate
H2: mamal cloth 65
A3: 1" 444 BRUSH | B3: 25mm | C3: 35 | D3: 65 | H3: paitn brush 25/50/75mm 35/70/105
A4: 2" 444 BRUSH | B4: 50mm | C4: 70 | D4: 130 | H4: abbrasive roll paper 17
A5: 3" 444 BRUSH | B5: 75mm | C5: 105 | D5: 195 | H5: abbrasive water paper 22
A6: 4" 444 BRUSH | B6: 100mm | C6: 140 | D6: 260 | H6: masking tape 1" 44
A7: fevicol | B7: 1kg | D7: 450 | H7: tarpin oil 239
A8: fevicol | B8: 0.5kg | D8: 250 | H8: paint roller 7" 177
A9: Pack thinner | B9: 1 | D9: 375 | H9: wire brush 49
A10: wheel khaksi GRINDER | B10: 1 | D10: 10 | H10: base wood polish 487
A11: water khaksi | B11: 1 | D11: 25
A12: paper khaksi | B12: 1 | D12: 5
A13: meter khaksi | B13: 1 | D13: 60
A14: wheel khaksi | B14: 1 | D14: 40
A15: Chalk powder | B15: 1kg | D15: 40
A16: Brown | B16: 1pkt 250gm | D16: 35
A17: Ramtilak | B17: 1pkt 250gm | D17: 35
A18: orange | B18: 1pkt | D18: 25 | E18: 800gm 70
A19: Geru | B19: 1pkt 400gm | D19: 35
A20: Kapada | B20: 1m | D20: 75
A21: Tarpin | B21: 700ml | D21: 100
A22: sprit | B22: 5lt | D22: 450
A23: sprit | B23: 1lt | D23: 100
A24: white cement | B24: 1kg | D24: 55
A25: Tar Brush | B25: 1pcs | D25: 60
A26: PERISH BLADE | B26: 1pcs | D26: 40
A27: NC thinner (B) | B27: 1lt | D27: 180
A28: masking tape 1" | B28: 1 | D28: 60
A29: PU GLOSSY SIRICA | B29: 1lt | C29: 2125 | D29: 2400
A30: PU MATT SIRICA | B30: 1lt | D30: 1650
A31: PU wood quote | B31: 1lt | D31: 1500
A32: SCRAPER (JK) GURUMALA | B32: 1 | C32: 70 | D32: 150
A33: PERISH BLADE WITH HANDLE | B33: 1 | C33: 70 | D33: 125
A35: wall putty | B35: 1bag | D35: 1200
A36: chapra readymade | B36: 1 LTR | D36: 600
A37: chapra readymade | B37: 0.5lt | D37: 325
A38: chapra | B38: 1kg | D38: 1600
A39: NC Metal putty | B39: 200gm | D39: 150
A40: sunlight slicon water base | B40: 1lt | C40: 625 | D40: 700
A41: sunlac slicon thinner base | B41: 1lt | C41: 800 | D41: 1000
A42: venezia gold | B42: 100ml | C42: 250 | D42: 400
A43: venezia gold | B43: 200ml | C43: 450 | D43: 750
A44: venezia gold | B44: 500ml | C44: 1100 | D44: 1700
A45: venezia gold | B45: 1lt | C45: 2200 | D45: 3200
A46: PERISH | B46: 1kg | D46: 40
A47: pge gold 01 | B47: 1 | D47: 3200
A48: pge gold 0.5 | B48: 1 | D48: 1700
A49: PGE Gold | B49: 100ml | D49: 375
A50: PGE Gold | B50: 200 | D50: 700
A51: marble cutter | B51: 1 | D51: 250
A52: RED OXIDE | B52: 1kg | D52: 150
A53: SPRAY PAINT/ (RGB) | B53: 1 | D53: 350
A54: pen brush | B54: 1 | D54: 100
A55: Black japan | B55: 1 | D55: 450
A56: Black japan | B56: 0.5 | D56: 250
A57: NC Metal putty | B57: 200gm | C57: 125 | D57: 150
A58: NC Metal putty | B58: 500gm | C58: 200 | D58: 250
A59: NC Metal putty | B59: 1kg | C59: 375 | D59: 450
A60: sirca melamine glossy | B60: 1 | C60: 960 | D60: 1000
A61: sirca melamine matt | B61: 1 | D61: 1050
A62: sirca melamine sealer | B62: 1 | D62: 900
A63: paint remover | B63: 1 | C63: 500 | D63: 600
A64: pu thinner | B64: 1 | D64: 550
A65: sheenlac wood polish wallnut | B65: 1 | D65: 600
A66: sirica wood stand | B66: 100ml | D66: 175
A67: wall nut | B67: 100ml | D67: 150
A68: Indigo copper | B68: 100ml | D68: 400
A69: Indigo copper | B69: 50ml | D69: 225
A70: Indigo gold | B70: 50ml | D70: 225
A71: HATO GOLD | B71: 300ML | D71: 1350
A72: HATO GOLD | B72: 1 | D72: 4000
A73: BEGER SILICON | B73: 0.875 | D73: 1000
A74: BEGER SILICON | B74: 3.5 | D74: 3900
A75: WOOD FILLER WALLNUT | B75: 1 | C75: 450 | D75: 550
A76: steel jhus | B76: 1 | D76: 150
A77: GLOBES COTON WHITE | B77: 1 | D77: 35
A78: GLOBES COTON COLOUR | B78: 1 | D78: 75
A79: GLOBES RABER | B79: 1 | D79: 90
A80: DORI | B80: 1 | D80: 8
A81: DR. FIXT FEVIMATE | B81: 500GM | C81: 70 | D81: 90
A82: DR. FIXT CRACK-X PASTE | B82: 1 | D82: 650
A83: shangrila black japan | B83: 500ml | D83: 250
A84: shangrila black japan | B84: 1 | D84: 450
A85: shangrila black board | B85: 500ml | C85: 210 | D85: 300
A86: shangrila black board | B86: 1 | C86: 390 | D86: 550
A87: sirica wood filler teak | B87: 1kg | D87: 500
A88: sirica wood filler wallnut | B88: 1kg | D88: 500
A89: sirica wood filler white | B89: 1kg | D89: 500
A90: HATO GOLD | B90: 150ml | D90: 750
A91: HATO GOLD | B91: 100ml | D91: 550
A92: pu sealer sunlac | B92: 1 | D92: 1950
A93: CUP BURSH | B93: 1 | D93: 125
A94: fiber glass tape/jali tape | B94: 1 | D94: 250
A95: Asian Crack Seal | B95: 1 | D95: 750
A96: bodhi gold | B96: 200 | D96: 750
A97: bodhi gold | B97: 100 | D97: 400
A98: bodhi gold | B98: 500 | C98: 1450 | D98: 1700
A99: Dr. Crack paste | B99: 1 | D99: 700
A100: fevimate/Tile Mate/Grout | B100: 1kg | D100: 150
A101: Black Board paint | B101: 1 | C101: 395 | D101: 550
...

Sheet Sheet2
A1: 66039 | B1: M/1767 | C1: EARTH CONSTRUCTION | D1: 11290
A2: 66057 | B2: M/1923 | C2: EARTH CONSTRUCTION | D2: 11290
A3: 66057 | B3: M/1925 | C3: EARTH CONSTRUCTION | D3: 25245
A4: 66058 | B4: M/1936 | C4: EARTH CONSTRUCTION | D4: 14363
A5: 66059 | B5: M/1943 | C5: EARTH CONSTRUCTION | D5: 13548
A6: 66062 | B6: M/1980 | C6: EARTH CONSTRUCTION | D6: 8572
A7: 66064 | B7: M/1995 | C7: EARTH CONSTRUCTION | D7: 11263

Sheet Sheet4
A1: Valley Paints
A2: 078-7-16 | B2: sales | C2: 12860
A3: 078-10-21 | B3: sales | C3: 4750
A4: 078-10-25 | B4: sales | C4: 7190
A5: 078-12-25 | B5: sales | C5: 2200
A6: 078-12-25 | B6: sales | C6: 270
A7: 078-12-27 | B7: sales | C7: 1650
A8: 078-12-27 | B8: sales | C8: 270
A9: 078-12-28 | B9: sales | C9: 2460
A10: 078-12-30 | B10: sales | C10: 7195
A11: 079-1-2 | B11: sales | C11: 20400
A12: 079-1-2 | B12: sales | C12: 3365
A13: 079-1-3 | B13: sales | C13: 3175
... A21: 079-2-5 | B21: cash | C21: -60000
C22: =SUM(C2:C21) -> 79120

Sheet dinesh
A1: ARMY SCHOOL | C1: sales | G1: PARLIAMENT
A2: AD1 20KG | B2: 2996 | C2: 3050 | G2: TE1 20L | H2: 4127
A3: EXT PRIMER 20 | B3: 4985 | C3: 5100 | G3: DCP 20 | H3: 2855
A4: DCP 20 | B4: 3059 | C4: 3100 | G4: AMPRO 20L | H4: 6115
A5: PGE LEAF BROWN 4L | B5: 2580 | C5: 2600 | G5: PGE BLACK 4L | H5: 2440
A6: AC1 20L | B6: 5063 | C6: 5150 | G6: PGE BLAZ WHITE | H6: 2725
A7: PGE WHITE 4L | B7: 2859 | C7: 2900

Sheet STOCK
C1: SHOP | D1: GODOWN
A2: ACE AC1 | B2: 1
A3: ACE AC1 | B3: 4
A4: ACE AC1 | B4: 10
A5: ACE AC1 | B5: 20
A6: ACE AC6 | B6: 1
A7: ACE AC6 | B7: 4
A8: ACE AC6 | B8: 10
A9: ACE AC6 | B9: 20
A10: ACE AC10 | B10: 1
A11: ACE AC10 | B11: 4
A12: ACE AC10 | B12: 10
A13: ACE AC10 | B13: 20
... A39: APEX AB6 | B39: 1
A40: 65744 | B40: 4
A41: APEX AB6 | B41: 10
A42: APEX AB6 | B42: 20
A43: APEX AB10 | B43: 1
A44: APEX AB10 | B44: 4
A45: APEX AB10 | B45: 10
A46: APEX AB10 | B46: 20
A47: APEX AB17 | B47: 1
A48: APEX AB17 | B48: 4
A49: APEX AB17 | B49: 10
A50: APEX AB17 | B50: 20
A51: APEX AB18 | B51: 1
A52: APEX AB18 | B52: 4
... A95: APEX ULTIMA HQ20 | B95: 20
C96: SHOP | D96: GODWON
A97: ULTIMA PROTEK UP1 | B97: 1
A98: ULTIMA PROTEK UP1 | B98: 4
A99: ULTIMA PROTEK UP1 | B99: 10
A100: ULTIMA PROTEK UP1 | B100: 20
A101: ULTIMA PROTEK UP10 | B101: 1
A102: ULTIMA PROTEK UP10 | B102: 4
A103: ULTIMA PROTEK UP10 | B103: 10
A104: ULTIMA PROTEK UP10 | B104: 20
A105: ULTIMA PROTEK UP13 | B105: 1
A106: ULTIMA PROTEK UP13 | B106: 4
A107: ULTIMA PROTEK UP13 | B107: 10
A108: ULTIMA PROTEK UP13 | B108: 20
... A126: ULTIMA PROTEK PS13/20 | B126: 20
D127: GODOWN
A128: ULTIMA CLEAR
A129: ULTIMA CLEAR | B129: 1
A130: ULTIMA CLEAR | B130: 4
A131: ULTIMA CLEAR | B131: 10
A133: DAMP DEFENSE DD01 | B133: 1
A134: DAMP DEFENSE DD01 | B134: 4
A135: DAMP DEFENSE DD01 | B135: 10
A136: DAMP DEFENSE DD01 | B136: 20
A137: DAMP DEFENSE DD10 | B137: 1
A138: DAMP DEFENSE DD10 | B138: 4
A139: DAMP DEFENSE DD10 | B139: 10
A140: DAMP DEFENSE DD10 | B140: 20
A141: DAMP DEFENSE DD20 | B141: 1
... A144: DAMP DEFENSE DD20 | B144: 20
C145: SHOP | D145: GODOWN
A146: TRACTOR TE1 | B146: 1
A147: TRACTOR TE1 | B147: 4
A148: TRACTOR TE1 | B148: 10
A149: TRACTOR TE1 | B149: 20
A150: TRACTOR TE6 | B150: 1
A151: TRACTOR TE6 | B151: 4
A152: TRACTOR TE6 | B152: 10
A153: TRACTOR TE6 | B153: 20
A154: TRACTOR TE13 | B154: 1
A155: TRACTOR TE13 | B155: 4
A156: TRACTOR TE13 | B156: 10
A157: TRACTOR TE13 | B157: 20
... A165: TRACTOR TE20 | B165: 20
C166: SHOP | D166: GODOWN
A167: PREMIUM BW1 | B167: 1
A168: PREMIUM BW1 | B168: 4
A169: PREMIUM BW1 | B169: 10
A170: PREMIUM BW1 | B170: 20
A171: PREMIUM BW6 | B171: 1
A172: PREMIUM BW6 | B172: 4
A173: PREMIUM BW6 | B173: 10
A174: PREMIUM BW6 | B174: 20
A175: PREMIUM BW10 | B175: 1
A176: PREMIUM BW10 | B176: 4
A177: PREMIUM BW10 | B177: 10
A178: PREMIUM BW10 | B178: 20
... A194: PREMIUM BW22 | B194: 20
C195: SHOP | D195: GODOWN
A197: ROYAL RB1 | B197: 1
A198: ROYAL RB1 | B198: 4
A199: ROYAL RB1 | B199: 10
A200: ROYAL RB1 | B200: 20
A201: ROYAL RB6 | B201: 1
A202: ROYAL RB6 | B202: 4
A203: ROYAL RB6 | B203: 10
A204: ROYAL RB6 | B204: 20
A205: ROYAL RB10 | B205: 1
A206: ROYAL RB10 | B206: 4
A207: ROYAL RB10 | B207: 10
A208: ROYAL RB10 | B208: 20
... A224: ROYAL RB22 | B224: 20
C225: SHOP | D225: GODOWN
...

Sheet STOK 1
A1: item | B1: QNT | C1: shop | D1: Godown | E1: Total
A2: paper khakshi(filint paper)
A3: Roll Khakshi(aAbrasive cloth Roll)
A4: Water Paper
A5: Sheelac chapara (base wood polish) | B5: 1LTR
A6: Sheelac chapara (base wood polish) | B6: 500ML
A7: Duco thinner | B7: 1LTR
A8: Duco sealer | B8: 1LTR
A9: Duco Laquer | B9: 1LTR
A10: Woow fin | B10: 1LTR
A11: Woow fin | B11: 500ML
A12: Woow fin | B12: 200ML
A13: Relaince black japan | B13: 1LTR
A14: Relaince black japan | B14: 500ML
A15: Relaince black board | B15: 1LTR | G15: dealer123
A16: Relaince black board | B16: 500ML
A17: Sirica Melamine Glossy | B17: 1LTR
A18: Sirica Melamine matt | B18: 1LTR
A19: Sirica pu glossy | B19: 1LTR
A20: Sirica pu sealer | B20: 1LTR
A21: Sirica Wood Staner | B21: 100ml
A22: Sirica Sealer | B22: 1LTR
A23: Sirica Thinner | B23: 1LTR
A24: Sunlac Sealer | B24: 1LTR
A25: Sunlac silicon | B25: 1LTR
A26: Sunlac silicon | B26: 20LTR
A27: Sunlac Ext PU Glossy | B27: 1LTR
... A64: Paint Bursh 444 1" | B64: 1"
A65: Paint Bursh 444 2"
A66: Paint Bursh 444 3"
A67: Paint Bursh 444 4"
A68: Paint Bursh 555 1"
A69: Paint Bursh 555 2"
A70: Paint Bursh 555 3"
A71: Paint Bursh 555 4"
A72: Wire Bursh
A73: Paint Roller 7"
A74: Paint Roller 4"
A75: Paint Roller 2"
A76: Spray paint
... A80: Kapada (cleaning cloth)
A81: Hato silicon | B81: 1
A82: Hato silicon | B82: 4
A83: J K White Cement | B83: 40 KG
A84: J K White Cement | B84: 5 KG
A85: J K White Cement | B85: 1 KG
A86: motolac sanding sraler | B86: 1LTR
A87: Sunlith silicon WT | B87: 1LTR
A88: miter khakshi
A89: perish

Sheet Sheet128

Sheet Sheet129

Sheet Sheet130

Sheet Sheet131

Sheet Sheet132

Sheet Sheet133

Sheet Sheet134

Sheet Sheet135

Sheet Sheet136

Sheet Sheet137

Sheet Sheet138

Sheet Sheet139

Sheet Sheet140

Sheet Sheet141

Sheet Sheet142

Sheet Sheet143

Sheet Sheet144

Sheet Sheet60
A1: TranDate | B1: Description | C1: ValueDate | D1: Debit | E1: Credit | F1: Balance | G1: TranId
A2: 8/13/2024 | B2: 222232FPQR-171569264-3560-54FPQR-171569264-3560 | C2: 8/13/2024 | E2: 3000 | G2: HPP030744063
A3: 8/13/2024 | B3: 222232FPQR-171688056-3561-54FPQR-171688056-3561 | C3: 8/13/2024 | E3: 2050 | G3: HPP131814720
A4: 8/13/2024 | B4: 222232FPQR-171768747-3562-54FPQR-171768747-3562 | C4: 8/13/2024 | E4: 3935 | G4: HPP175545877
A5: 8/13/2024 | B5: ASIAN PAINTS NEPAL PVT LTDINC:ECC 259211 | C5: 8/13/2024 | D5: 1200000 | G5: 6154041
A6: 8/13/2024 | B6: CHQ. DEP-THE GS TRADE | C6: 8/13/2024 | E6: 800000 | G6: 144144918
A7: 8/13/2024 | B7: DEP-RAJENDRA SHRESTHA | C7: 8/13/2024 | E7: 300000 | G7: 144115418
A8: 8/13/2024 | B8: ~ Date summary | F8: 75924.18
A9: 8/14/2024 | B9: 222232FPQR-171909315-3563-54FPQR-171909315-3563 | C9: 8/14/2024 | E9: 20000 | G9: HPP023648267
A10: 8/14/2024 | B10: 222232FPQR-172026894-3564-54FPQR-172026894-3564 | C10: 8/14/2024 | E10: 1450 | G10: HPP125108137
A11: 8/14/2024 | B11: 222232FPQR-172108283-3565-54FPQR-172108283-3565 | C11: 8/14/2024 | E11: 36290 | G11: HPP172729187
A12: 8/14/2024 | B12: ~ Date summary | F12: 133664.18
A13: 8/15/2024 | B13: 222232FPQR-172248486-3566-54FPQR-172248486-3566 | C13: 8/15/2024 | E13: 37625 | G13: HPP022311783
A14: 8/15/2024 | B14: 222232FPQR-172447223-3568-54FPQR-172447223-3568 | C14: 8/15/2024 | E14: 5120 | G14: HPP170023340
A15: 8/15/2024 | B15: ~ Date summary | F15: 176409.18
A16: 8/16/2024 | B16: 222232FPQR-172588029-3569-54FPQR-172588029-3569 | C16: 8/16/2024 | E16: 8125 | G16: HPP041254090
A17: 8/16/2024 | B17: 222232FPQR-172706277-3570-54FPQR-172706277-3570 | C17: 8/16/2024 | E17: 2070 | G17: HPP124949367
A18: 8/16/2024 | B18: 222232FPQR-172787008-3571-54FPQR-172787008-3571 | C18: 8/16/2024 | E18: 6300 | G18: HPP175331257
A19: 8/16/2024 | B19: MPBL40544138 | C19: 8/16/2024 | E19: 65155 | G19: 147151056
A20: 8/16/2024 | B20: NIBL3029780419 | C20: 8/16/2024 | E20: 40200 | G20: 147151056
A21: 8/16/2024 | B21: NICA70932082 | C21: 8/16/2024 | E21: 46019.02 | G21: 147151056
A22: 8/16/2024 | B22: ~ Date summary | F22: 344278.2
A23: 8/17/2024 | B23: 222232FPQR-172927898-3572-54FPQR-172927898-3572 | C23: 8/17/2024 | E23: 6235 | G23: HPP024217760
A24: 8/17/2024 | B24: ~ Date summary | F24: 350513.2
A25: 8/18/2024 | B25: 222232FPQR-173119649-3574-FPQR-173119649-3574:OFF | C25: 8/18/2024 | E25: 500 | G25: HPP175050963
A26: 8/18/2024 | B26: 222232FPQR-173316153-3576-54FPQR-173316153-3576 | C26: 8/18/2024 | E26: 1575 | G26: HPP131454020
A27: 8/18/2024 | B27: 222232FPQR-173398466-3577-54FPQR-173398466-3577 | C27: 8/18/2024 | E27: 3560 | G27: HPP181103340
A28: 8/18/2024 | B28: TERAI TRADERSINC:ECC 259225 | C28: 8/18/2024 | D28: 25000 | G28: 6150707
A29: 8/18/2024 | B29: ~ Date summary | F29: 331148.2
A30: 8/19/2024 | B30: 222232FPQR-173539300-3578-54FPQR-173539300-3578 | C30: 8/19/2024 | E30: 15275 | G30: HPP033234787
A31: 8/19/2024 | B31: 222232FPQR-173655514-3579-54FPQR-173655514-3579 | C31: 8/19/2024 | E31: 25000 | G31: HPP122304070
A32: 8/19/2024 | B32: ASIAN PAINTS NEPAL PVT LTD INC:ECC 259214 | C32: 8/19/2024 | D32: 1100000 | G32: 5150800
A33: 8/19/2024 | B33: DEP-RAJENDRA SHRESTHA | C33: 8/19/2024 | E33: 625000 | G33: 4122832
A34: 8/19/2024 | B34: DEP-RAJENDRA SHRESTHA | C34: 8/19/2024 | E34: 106000 | G34: 134131631
A35: 8/19/2024 | B35: ~ Date summary | F35: 2423.2
A36: 8/20/2024 | B36: 222232FPQR-173731376-3580-54FPQR-173731376-3580 | C36: 8/20/2024 | E36: 20600 | G36: HPP185406700
A37: 8/20/2024 | B37: 222232FPQR-173924256-3582-54FPQR-173924256-3582 | C37: 8/20/2024 | E37: 4930 | G37: HPP125850823
A38: 8/20/2024 | B38: 222232FPQR-173970989-3583-54FPQR-173970989-3583 | C38: 8/20/2024 | E38: 7865 | G38: HPP174003533
A39: 8/20/2024 | B39: ~ Date summary | F39: 35818.2
A40: 8/21/2024 | B40: 222232FPQR-174045848-3584-54FPQR-174045848-3584 | C40: 8/21/2024 | E40: 28660 | G40: HPP023826670
A41: 8/21/2024 | B41: 222232FPQR-174211270-3586-54FPQR-174211270-3586 | C41: 8/21/2024 | E41: 29375 | G41: HPP185030510
A42: 8/21/2024 | B42: ECC O/W CHQ CHRG | C42: 8/21/2024 | D42: 16.95 | G42: 144174947
A43: 8/21/2024 | B43: SIFL522458 | C43: 8/21/2024 | E43: 1500000 | G43: 144174943
A44: 8/21/2024 | B44: ~ Date summary | F44: 1593836.2
A45: 8/22/2024 | B45: 222232FPQR-174286350-3587-54FPQR-174286350-3587 | C45: 8/22/2024 | E45: 14780 | G45: HPP034905940
A46: 8/22/2024 | B46: 222232FPQR-174485847-3589-54FPQR-174485847-3589 | C46: 8/22/2024 | E46: 25760 | G46: HPP175220450
A47: 8/22/2024 | B47: ~ Date summary | F47: 1634376.2
A48: 8/23/2024 | B48: 222232FPQR-174626596-3590-54FPQR-174626596-3590 | C48: 8/23/2024 | E48: 7500 | G48: HPP033848827
A49: 8/23/2024 | B49: 741545THE G.S. TRADE NPRK0452 NPR10673-CIPS | C49: 8/23/2024 | D49: 200000 | G49: HPP150231590
A50: 8/23/2024 | B50: ~ Date summary | F50: 1441876.2
A51: 8/24/2024 | B51: 222232FPQR-174825687-3592-FPQR-174825687-3592:OFF | C51: 8/24/2024 | E51: 21000 | G51: HPP174731597
A52: 8/24/2024 | B52: ~ Date summary | F52: 1462876.2
A53: 8/25/2024 | B53: 137421THE G.S. TRADE NPRK0452 npr10673-CIPS | C53: 8/25/2024 | D53: 500000 | G53: HPP114106810
A54: 8/25/2024 | B54: 222232FPQR-175157615-3595-54FPQR-175157615-3595 | C54: 8/25/2024 | E54: 2095 | G54: HPP184326300
A55: 8/25/2024 | B55: 222232FPQR-175436047-3598-54FPQR-175436047-3598 | C55: 8/25/2024 | E55: 2425 | G55: HPP184114430
A56: 8/25/2024 | B56: TERAI TRADERSINC:ECC 259227 | C56: 8/25/2024 | D56: 25000 | G56: 6152658
A57: 8/25/2024 | B57: ~ Date summary | F57: 942396.25
A58: 8/26/2024 | B58: 222232FPQR-175576504-3599-54FPQR-175576504-3599 | C58: 8/26/2024 | E58: 4250 | G58: HPP021751080
A59: 8/26/2024 | B59: 222232FPQR-175693159-3600-54FPQR-175693159-3600 | C59: 8/26/2024 | E59: 19800 | G59: HPP133626427
A60: 8/26/2024 | B60: ~ Date summary | F60: 966446.25
A61: 8/27/2024 | B61: 222232FPQR-175773306-3601-54FPQR-175773306-3601 | C61: 8/27/2024 | E61: 13000 | G61: HPP193823020
A62: 8/27/2024 | B62: 222232FPQR-175911511-3602-54FPQR-175911511-3602 | C62: 8/27/2024 | E62: 4740 | G62: HPP025940727
A63: 8/27/2024 | B63: 222232FPQR-176032200-3603-54FPQR-176032200-3603 | C63: 8/27/2024 | E63: 2200 | G63: HPP121302217
A64: 8/27/2024 | B64: 222232FPQR-176113587-3604-54FPQR-176113587-3604 | C64: 8/27/2024 | E64: 400 | G64: HPP172636627
A65: 8/27/2024 | B65: AAVIK IMPEX PVT LTDINC:ECC 259226 | C65: 8/27/2024 | D65: 940 | G65: 6153053
A66: 8/27/2024 | B66: ECC O/W CHQ CHRG | C66: 8/27/2024 | D66: 16.95 | G66: 141175258
A67: 8/27/2024 | B67: NIBL3030320531 | C67: 8/27/2024 | E67: 219010 | G67: 141175250
A68: 8/27/2024 | B68: ~ Date summary | F68: 1204839.3
A69: 8/28/2024 | B69: 222232FPQR-176452511-3607-54FPQR-176452511-3607 | C69: 8/28/2024 | E69: 11700 | G69: HPP175435143
A70: 8/28/2024 | B70: ASIAN PAINTS NEPAL PVT LTDINC:ECC 261505 | C70: 8/28/2024 | D70: 500000 | G70: 6113102
A71: 8/28/2024 | B71: ~ Date summary | F71: 716539.3
A72: 8/29/2024 | B72: 222232FPQR-176711088-3609-54FPQR-176711088-3609 | C72: 8/29/2024 | E72: 6880 | G72: HPP132114093
A73: 8/29/2024 | B73: 222232FPQR-176791837-3610-54FPQR-176791837-3610 | C73: 8/29/2024 | E73: 19750 | G73: HPP182104813
A74: 8/29/2024 | B74: ADBL30634629 | C74: 8/29/2024 | E74: 108930 | G74: 141172259
A75: 8/29/2024 | B75: ADBL30634629 UNRLZ | C75: 8/29/2024 | D75: 108930 | G75: 141172316
A76: 8/29/2024 | B76: ~ Date summary | F76: 743169.3
A77: 8/30/2024 | B77: 222232FPQR-176931492-3611-54FPQR-176931492-3611 | C77: 8/30/2024 | E77: 700 | G77: HPP041619500
A78: 8/30/2024 | B78: 222232FPQR-177050781-3612-54FPQR-177050781-3612 | C78: 8/30/2024 | E78: 2200 | G78: HPP114215917
A79: 8/30/2024 | B79: 914957THE G.S. TRADE NPRK0452 Npr10673-CIPS | C79: 8/30/2024 | D79: 1000000 | G79: HPP152734357
A80: 8/30/2024 | B80: CHQ DEP-THE GS TRADE | C80: 8/30/2024 | E80: 300000 | G80: 144124751
A81: 8/30/2024 | B81: ~ Date summary | F81: 46069.3
A82: 8/31/2024 | B82: 222232FPQR-177131699-3613-54FPQR-177131699-3613 | C82: 8/31/2024 | E82: 7725 | G82: HPP193026887
A83: 8/31/2024 | B83: 222232FPQR-177464392-3616-54FPQR-177464392-3616 | C83: 8/31/2024 | E83: 70175 | G83: HPP175806710
A84: 8/31/2024 | B84: ~ Date summary | F84: 123969.3
A85: 45300 | B85: 222232FPQR-177741705-3619-54FPQR-177741705-3619 | C85: 45300 | E85: 21040 | G85: HPP183809170
A86: 45300 | B86: TERAI TRADERSCLG TFR 261515 | C86: 45300 | D86: 25000 | G86: 6153500
A87: 45300 | B87: ~ Date summary | F87: 120009.3
A88: 45331 | B88: 222232FPQR-177883484-3620-54FPQR-177883484-3620 | C88: 45331 | E88: 9375 | G88: HPP044846817
A89: 45331 | B89: 222232FPQR-178001640-3621-54FPQR-178001640-3621 | C89: 45331 | E89: 750 | G89: HPP144759127
A90: 45331 | B90: 222232FPQR-178081781-3622-54FPQR-178081781-3622 | C90: 45331 | E90: 99485 | G90: HPP181255483
A91: 45331 | B91: CITIZENS30483903 | C91: 45331 | E91: 1650.93 | G91: 141173601
A92: 45331 | B92: NIBL3030377906 | C92: 45331 | E92: 60000 | G92: 141173601
A93: 45331 | B93: PBL46184634 | C93: 45331 | E93: 150000 | G93: 141173601
A94: 45331 | B94: ~ Date summary | F94: 441270.23
A95: 45360 | B95: 252807sapati ACCOUNTFT:RAJENDRA SHRESTHA-CIPS | C95: 45360 | E95: 2000 | G95: HPP164938160
A96: 45360 | B96: 257497THE G.S. TRADE NPRK0452 NPR10673-CIPS | C96: 45360 | D96: 1000000 | G96: HPP165444807
A97: 45360 | B97: CHQ. DEP-THE GS TRADE | C97: 45360 | E97: 333000 | G97: 144161738
A98: 45360 | B98: DEP-RAJENDRA SHRESTHA | C98: 45360 | E98: 226000 | G98: 144161711
A99: 45360 | B99: ~ Date summary | F99: 2270.23
A100: 45391 | B100: 222232FPQR-178420586-3625-FPQR-178420586-3625:OFF | C100: 45391 | E100: 44000 | G100: HPP194958950
...

Sheet Sheet63

Sheet Sheet64

Sheet Sheet65

Sheet Sheet66

Sheet Sheet67

Sheet Sheet68

Sheet Sheet69

Sheet Sheet70

Sheet Sheet71

Sheet Sheet72

Sheet Sheet73

Sheet Sheet74

Sheet Sheet75

Sheet Sheet76

Sheet Sheet77

Sheet Sheet78

Sheet Sheet79

Sheet Sheet80

Sheet Sheet81

Sheet Sheet82

Sheet Sheet83

Sheet Sheet84

Sheet Sheet85

Sheet Sheet86

Sheet Sheet87

Sheet Sheet88

Sheet Sheet89

Sheet Sheet90

Sheet Sheet91

Sheet Sheet92

Sheet Sheet93

Sheet Sheet94

Sheet Sheet95

Sheet Sheet96

Sheet Sheet97

Sheet Sheet98

Sheet Sheet99

Sheet Sheet100

Sheet Sheet101

Sheet Sheet102

Sheet Sheet103

Sheet Sheet104

Sheet Sheet105

Sheet Sheet106

Sheet Sheet107

Sheet Sheet108

Sheet Sheet109

Sheet Sheet110

Sheet Sheet111

Sheet Sheet112

Sheet Sheet113

Sheet Sheet114

Sheet Sheet115

Sheet Sheet116

Sheet Sheet117

Sheet Sheet118

Sheet Sheet119

Sheet Sheet120

Sheet Sheet121

Sheet Sheet122

Sheet Sheet123

Sheet Sheet61

Sheet Sheet62

Sheet Sheet34
C1: SHOP | D1: GODOWN
A2: Shyne SN2 | B2: 1
A3: Shyne SN2 | B3: 4
A4: Shyne SN2 | B4: 10
A5: Shyne SN2 | B5: 20
A6: Shyne SN7 | B6: 1
A7: Shyne SN7 | B7: 4
A8: Shyne SN7 | B8: 10
A9: Shyne SN7 | B9: 20
A10: Shyne SN11 | B10: 1
A11: Shyne SN11 | B11: 4
A12: Shyne SN11 | B12: 10
A13: Shyne SN11 | B13: 20
... A25: Shyne SN22 | B25: 20
C26: SHOP | D26: GODOWN
A27: DAMP DEFENSE DD01 | B27: 1
A28: DAMP DEFENSE DD01 | B28: 4
A29: DAMP DEFENSE DD01 | B29: 10
A30: DAMP DEFENSE DD01 | B30: 20
A31: DAMP DEFENSE DD10 | B31: 1
A32: DAMP DEFENSE DD10 | B32: 4
A33: DAMP DEFENSE DD10 | B33: 10
A34: DAMP DEFENSE DD10 | B34: 20
A35: DAMP DEFENSE DD20 | B35: 1
A36: DAMP DEFENSE DD20 | B36: 4
A37: DAMP DEFENSE DD20 | B37: 10
A38: DAMP DEFENSE DD20 | B38: 20
C39: SHOP | D39: GODOWN
A40: PREMIUM BW1 | B40: 1
A41: PREMIUM BW1 | B41: 4
A42: PREMIUM BW1 | B42: 10
A43: PREMIUM BW1 | B43: 20
A44: PREMIUM BW6 | B44: 1
A45: PREMIUM BW6 | B45: 4
A46: PREMIUM BW6 | B46: 10
A47: PREMIUM BW6 | B47: 20
A48: PREMIUM BW10 | B48: 1
A49: PREMIUM BW10 | B49: 4
A50: PREMIUM BW10 | B50: 10
A51: PREMIUM BW10 | B51: 20
... A73: APEX AB6 | B73: 1
A74: 65744 | B74: 4
A75: APEX AB6 | B75: 10
A76: APEX AB6 | B76: 20
A77: APEX AB10 | B77: 1
A78: APEX AB10 | B78: 4
A79: APEX AB10 | B79: 10
A80: APEX AB10 | B80: 20
A81: APEX AB17 | B81: 1
A82: APEX AB17 | B82: 4
A83: APEX AB17 | B83: 10
A84: APEX AB17 | B84: 20
A85: APEX AB18 | B85: 1
A86: APEX AB18 | B86: 4
... A100: APEX AB20 | B100: 20

Sheet Sheet35
A1: PRODUCT | B1: UNIT | C1: BALANCE
A2: (DS) OHS 2F W/O ARM (OH110S) | B2: 1NOS | C2: 1
A3: 15"RFS ARM ROUND GOLD (RSSA715) | B3: 1NOS | C3: 0
A4: 15"RFS ARM ROUND NEW (SA105N) | B4: 1NOS | C4: 0
A5: 15"RFS ARM ROUND NEW (SA106N) | B5: 1NOS | C5: 0
A6: 18"RFS ARM ROUND NEW (SA107N) | B6: 1NOS | C6: 0
A7: 2 FUNCTION HS (RSTS103) | B7: 1NOS | C7: 0
A8: 20.3 CM RFS ROUND W/O ARM (8) (RF205) | B8: 1NOS | C8: 0
A9: 20.3 CM RFS SQUARE W/O ARM (8) (RF206) | B9: 1NOS | C9: 0
A10: 3.5" HS SQUARE WITH 1.5MTR FLEX TUBE & (HS205) | B10: 1NOS | C10: 0
A11: 4" HS, 1F WITH 1.5 MTR FLEX TUBE & HOO (HS202) | B11: 1NOS | C11: 0
A12: 4" OHS, 1F W/O ARM (OH202) | B12: 1NOS | C12: 0
A13: 9 INCH SELF CLEAN RF SHOWER (BHRF101) | B13: 1NOS | C13: 0
A14: 9 INCH SQUARE GOLD CLR SHOWER (RSRF702) | B14: 1NOS | C14: 0
A15: AB02 01 | B15: 1LTR | C15: 8 | D15: 800
A16: AB02 04 | B16: 4LTR | C16: 13 | D16: 2900
A17: AB02 10 | B17: 10LTR | C17: 1 | D17: 6900
A18: AB02 20 | B18: 20LTR | C18: 4 | D18: 13000
A19: AB06 01 | B19: 1LTR | C19: 0
A20: AB06 04 | B20: 4LTR | C20: 0
A21: AB06 10 | B21: 10LTR | C21: 0
A22: AB06 20 | B22: 20LTR | C22: 0
A23: AB10 01 | B23: 1LTR | C23: 11 | D23: 800
A24: AB10 04 | B24: 4LTR | C24: 1 | D24: 2900
A25: AB10 10 | B25: 10LTR | C25: 1 | D25: 6900
A26: AB10 20 | B26: 20LTR | C26: 4 | D26: 13000
A27: AB13 01 | B27: 1LTR | C27: 2 | D27: 700
A28: AB13 04 | B28: 4LTR | C28: 0
A29: AB13 10 | B29: 10LTR | C29: 0
A30: AB13 20 | B30: 20LTR | C30: 0
A31: AB15 01 | B31: 1LTR | C31: 11 | D31: 700
A32: AB15 04 | B32: 4LTR | C32: 6 | D32: 2500
A33: AB15 10 | B33: 10LTR | C33: 1 | D33: 6000
A34: AB15 20 | B34: 20LTR | C34: 1 | D34: 118000
A35: AB17 01 | B35: 1LTR | C35: 6 | D35: 800
A36: AB17 04 | B36: 4LTR | C36: 2 | D36: 2900
A37: AB17 10 | B37: 10LTR | C37: 0 | D37: 6900
A38: AB17 20 | B38: 20LTR | C38: 0
A39: AB18 01 | B39: 1LTR | C39: 0
A40: AB18 04 | B40: 4LTR | C40: 0
A41: AB18 10 | B41: 10LTR | C41: 0
A42: AB18 20 | B42: 20LTR | C42: 0
A43: AB20 01 | B43: 1LTR | C43: 1 | D43: 700
A44: AB20 04 | B44: 4LTR | C44: 5 | D44: 2500
A45: AB20 10 | B45: 10LTR | C45: 3 | D45: 6000
A46: AB20 20 | B46: 20LTR | C46: 1 | D46: 11500
A47: ABRASIVE CLOTH / PAPER ROLL (METER KHAKSI) | B47: 1MTR | C47: 0
A48: ABRASIVE CLOTH / PAPER ROLL (METER KHAKSI) PCS | B48: 1PCS | C48: 2377
A49: AC01 0.2 | B49: 0.2LT | C49: 0
A50: AC01 01 | B50: 1LTR | C50: 5 | D50: 1/DAMAGE
A51: AC01 04 | B51: 4LTR | C51: 6
A52: AC01 10 | B52: 10LTR | C52: 1
A53: AC01 20 | B53: 20LTR | C53: 2
A54: AC06 0.2 | B54: 0.2LT | C54: 0
A55: AC06 01 | B55: 1LTR | C55: 4
A56: AC06 04 | B56: 4LTR | C56: 0
A57: AC06 10 | B57: 10LTR | C57: 0
A58: AC06 20 | B58: 20LTR | C58: 0
A59: AC10 0.2 | B59: 0.2LT | C59: 0
A60: AC10 01 | B60: 1LTR | C60: 3
A61: AC10 04 | B61: 4LTR | C61: 1
A62: AC10 10 | B62: 10LTR | C62: 1
... A93: ALU PAINT 0.2 | B93: 0.2LT | C93: 0
A94: ALU PAINT 0.5 | B94: 0.5LT | C94: 7 | D94: 11/15-23/YES
A95: ALU PAINT 01 | B95: 1LTR | C95: 1 | D95: 11/15-6/YES
A96: ALU PAINT 01 (SUNLAC) | B96: 1LTR | C96: 3 | D96: YES
A97: ALUMINIUM PAINTS 0.5 (BABA) | B97: 0.5LT | C97: 0
A98: AMC EXT.RED 01 | B98: 1LTR | C98: 5
A99: AMC FAST BLACK 01 | B99: 1LTR | C99: 10
A100: AMC FAST BLUE 01 | B100: 1LTR | C100: 4
A101: AMC FAST GREEN 01 | B101: 1LTR | C101: 3
A102: AMC FAST YELLOW 01 | B102: 1LTR | C102: 5
A103: AMC HT BLUE 01 | B103: 1LTR | C103: 1
A104: AMC HT GREEN 01 | B104: 1LTR | C104: 4
A105: AMC HT REDOXIDE 01 | B105: 1LTR | C105: 5
A106: AMC HT VIOLET 01 | B106: 1LTR | C106: 2
A107: AMC HT WHITE 01 | B107: 1LTR | C107: 11
A108: AMC HT YELLOW 01 | B108: 1LTR | C108: 2
... A158: BIO BLOCK CLEAR 01 | B158: 1LTR | C158: 0
A159: BL01 01 | B159: 1LTR | C159: 0 | D159: 2/
A160: BL01 04 | B160: 4LTR | C160: 23
A161: BL01 10 | B161: 10LTR | C161: 0
A162: BL01 20 | B162: 20LTR | C162: 1
A163: BL10 01 | B163: 1LTR | C163: 5
A164: BL10 04 | B164: 4LTR | C164: 0
A165: BL10 10 | B165: 10LTR | C165: 0
A166: BL10 20 | B166: 20LTR | C166: 0
A167: BL13 01 | B167: 1LTR | C167: 0
A168: BL13 04 | B168: 4LTR | C168: 0
A169: BL13 10 | B169: 10LTR | C169: 0
A170: BLACK | B170: 1PKT | C170: 30
A171: BLACK (KOKILA) | B171: 1PCS | C171: 0
... A180: BLACK JAPAN 01 (SHANGRILA) | B180: 1LTR | C180: 0
A181: BLACK JAPAN 01 (WEMBLEY) | B181: #REF! | C181: 0
A182: BLACK JAPAN 04 (BABA) | B182: 4LTR | C182: 0
A183: BLACK JAPAN 04 (SHANGRILA) | B183: 4LTR | C183: 0
A184: BODY GRSLCD HIGH FLOW (GRDV202) | B184: 1NOS | C184: 0
A185: BODY ROYALE INSPIRE SLCD HF (B2DV202) | B185: 1NOS | C185: 0
A186: BOLT (JK) | B186: 1PCS | C186: 0
A187: BOND SET (BIG) (JK) | B187: 1PCS | C187: 0
...

Sheet Sheet59
A1: 45395 | B1: 7520.41 | C1: 21802604 | D1: Calc
A2: 45396 | B2: 7520.41 | C2: 21802604 | D2: Calc
A3: 45397 | B3: 7689.42 | C3: 22292604 | D3: Calc
A4: 45398 | B4: 7689.42 | C4: 22292604 | D4: Calc
A5: 45399 | B5: 7689.42 | C5: 22292604 | D5: Calc
A6: 45400 | B6: 7689.42 | C6: 22292604 | D6: Calc
A7: 45401 | B7: 7689.42 | C7: 22292604 | D7: Calc
A8: 45402 | B8: 7689.42 | C8: 22292604 | D8: Calc
A9: 45403 | B9: 7689.42 | C9: 22292604 | D9: Calc
A10: 45404 | B10: 7689.42 | C10: 22292604 | D10: Calc
A11: 45405 | B11: 7689.42 | C11: 22292604 | D11: Calc
A12: 45406 | B12: 7689.42 | C12: 22292604 | D12: Calc
... A94: 45488 | B94: 6165.21 | C94: 19249804 | D94: Calc
A95: 45488 | B95: 650366.92 | D95: Post

Sheet Sheet36

Sheet Sheet37

Sheet Sheet38

Sheet Sheet39

Sheet Sheet40

Sheet Sheet41

Sheet Sheet42

Sheet Sheet43

Sheet Sheet44

Sheet Sheet45

Sheet Sheet46

Sheet Sheet47

Sheet Sheet48

Sheet Sheet49

Sheet Sheet50

Sheet Sheet51

Sheet Sheet52

Sheet Sheet53

Sheet Sheet54

Sheet Sheet55

Sheet Sheet56

Sheet Sheet57

Sheet Sheet58

Sheet ODRE COMPANY
A1: ACE AC1 | B1: 1
A2: ACE AC1 | B2: 4
A3: ACE AC1 | B3: 10
A4: ACE AC1 | B4: 20
A5: ACE AC6 | B5: 1
A6: ACE AC6 | B6: 4
A7: ACE AC6 | B7: 10 | C7: 5
A8: ACE AC6 | B8: 20
A9: ACE AC10 | B9: 1
A10: ACE AC10 | B10: 4
A11: ACE AC10 | B11: 10 | C11: 5
A12: ACE AC10 | B12: 20
A13: ACE AC17 | B13: 1
A14: ACE AC17 | B14: 4
A15: ACE AC17 | B15: 10 | C15: 2
A16: ACE AC17 | B16: 20
A17: ACE AC18 | B17: 1
A18: ACE AC18 | B18: 4
A19: ACE AC18 | B19: 10
A20: ACE AC18 | B20: 20
A21: ACE AC13 | B21: 1 | C21: 12
A22: ACE AC13 | B22: 4 | C22: 4
A23: ACE AC13 | B23: 10 | C23: 5
A24: ACE AC13 | B24: 20 | C24: 5
A25: ACE AC15 | B25: 1
A26: ACE AC15 | B26: 4
A27: ACE AC15 | B27: 10 | C27: 6
A28: ACE AC15 | B28: 20 | C28: 5
A29: ACE AC20 | B29: 1
A30: ACE AC20 | B30: 4
A31: ACE AC20 | B31: 10 | C31: 5
A32: ACE AC20 | B32: 20 | C32: 5
A34: APEX AB2 | B34: 1
A35: APEX AB2 | B35: 4
A36: APEX AB2 | B36: 10
A37: APEX AB2 | B37: 20
A38: APEX AB6 | B38: 1
A39: 65744 | B39: 4
A40: APEX AB6 | B40: 10
A41: APEX AB6 | B41: 20
A42: APEX AB10 | B42: 1
A43: APEX AB10 | B43: 4
A44: APEX AB10 | B44: 10
A45: APEX AB10 | B45: 20
A46: APEX AB17 | B46: 1
A47: APEX AB17 | B47: 4
A48: APEX AB17 | B48: 10
A49: APEX AB17 | B49: 20
A50: APEX AB18 | B50: 1
A51: APEX AB18 | B51: 4
... A57: APEX AB13 | B57: 19.53
A58: APEX AB15 | B58: 0.97 | C58: 30
A59: APEX AB15 | B59: 3.9
A60: APEX AB15 | B60: 9.76
A61: APEX AB15 | B61: 19.53
A62: APEX AB20 | B62: 0.97
A63: APEX AB20 | B63: 3.9
A64: APEX AB20 | B64: 9.76
A65: APEX AB20 | B65: 19.53
A67: APEX ULTIMA HQ2 | B67: 1
A68: APEX ULTIMA HQ2 | B68: 4
A69: APEX ULTIMA HQ2 | B69: 10
A70: APEX ULTIMA HQ2 | B70: 20
A71: APEX ULTIMA HQ6 | B71: 1
... A124: ULTIMA PROTEK PS13/20 | B124: 10
B125: 20
A126: ULTIMA CLEAR
A127: ULTIMA CLEAR | B127: 1
A128: ULTIMA CLEAR | B128: 4
A129: ULTIMA CLEAR | B129: 10
B130: 20
A131: DAMP DEFENSE DD01 | B131: 1
A132: DAMP DEFENSE DD01 | B132: 4
A133: DAMP DEFENSE DD01 | B133: 10
A134: DAMP DEFENSE DD01 | B134: 20
A135: DAMP DEFENSE DD10 | B135: 1
A136: DAMP DEFENSE DD10 | B136: 4
A137: DAMP DEFENSE DD10 | B137: 10
A138: DAMP DEFENSE DD10 | B138: 20
A139: DAMP DEFENSE DD20 | B139: 1
A140: DAMP DEFENSE DD20 | B140: 4
A141: DAMP DEFENSE DD20 | B141: 10
A142: DAMP DEFENSE DD20 | B142: 20
... A298: ROYAL BLING BL13 | B298: 20
A300: TRACTOR AD1 | B300: 1 | C300: 30
A301: TRACTOR AD1 | B301: 5
A302: TRACTOR AD1 | B302: 10 | C302: 24
A303: TRACTOR AD1 | B303: 20
A304: TRACTOR AD6 | B304: 1
A305: TRACTOR AD6 | B305: 5
A306: TRACTOR AD6 | B306: 10
A307: TRACTOR AD6 | B307: 20
A309: TRACTOR AD10 | B309: 1
A310: TRACTOR AD10 | B310: 5
A311: TRACTOR AD10 | B311: 10
A312: TRACTOR AD10 | B312: 20
A314: UTSAV UD1 TRACTOR UNO | B314: 1 | C314: 30
A315: UTSAV UD1 TRACTOR UNO | B315: 5
A316: UTSAV UD1 TRACTOR UNO | B316: 10 | C316: 20
A317: UTSAV UD1 TRACTOR UNO | B317: 20
...

Sheet BATHSENSE SANWARE
A1: Material Desc | B1: Lower limit | C1: CATEGORY | D1: Sanware Item name | E1: New Price | F1: Excise % | G1: Vat % | H1: Excise amt. | I1: Vat amt. | J1: Final DP With Excise & Vat | K1: Discount % | L1: Dealer Margin | M1: Total Value after dealer margin | N1: Customer Discount | O1: MRP Raw | P1: Final MRP
A2: CONCEALED CISTERN & PUSH PLATE FOR WALL HUNG COMMODE
A3: CC W/O FAME CONCEALED | B3: BS-CC-B1 | C3: CONCEALED CISTERN | E3: 7920 | F3: 0.05 | G3: 0.13 | H3: =E3*F3 -> 396 | I3: =(E3+H3)*G3 -> 1081.08 | J3: =E3+H3+I3 -> 9397.08 | K3: 0.2 | L3: =J3*K3 -> 1879.416 | M3: =J3+L3 -> 11276.496 | N3: 0.2 | O3: =$M3/(1-N3) -> 14095.62 | P3: =MROUND(O3,10) -> 14100
A4: CONCEALED CISTERN WITH FRAME | B4: BS-CC-B2 | C4: CONCEALED CISTERN | E4: 12110 | F4: 0.05 | G4: 0.13 | H4: =E4*F4 -> 605.5 | I4: =(E4+H4)*G4 -> 1653.015 | J4: =E4+H4+I4 -> 14368.515 | K4: 0.2 | L4: =J4*K4 -> 2873.703 | M4: =J4+L4 -> 17242.218 | N4: 0.2 | O4: =$M4/(1-N4) -> 21552.772 | P4: =MROUND(O4,10) -> 21550
A5: CC SQUARE PLATE | B5: BS-PL-01 | C5: PUSH PLATE FOR CONCEALED CISTERN | E5: 1430 | F5: 0.05 | G5: 0.13 | H5: =E5*F5 -> 71.5 | I5: =(E5+H5)*G5 -> 195.195 | J5: =E5+H5+I5 -> 1696.695 | K5: 0.2 | L5: =J5*K5 -> 339.339 | M5: =J5+L5 -> 2036.034 | N5: 0.2 | O5: =$M5/(1-N5) -> 2545.0425 | P5: =MROUND(O5,10) -> 2550
A6: CC ROUND PLATE | B6: BS-PL-02 | C6: PUSH PLATE FOR CONCEALED CISTERN | E6: 1210 | F6: 0.05 | G6: 0.13 | H6: =E6*F6 -> 60.5 | I6: =(E6+H6)*G6 -> 165.165 | J6: =E6+H6+I6 -> 1435.665 | K6: 0.2 | L6: =J6*K6 -> 287.133 | M6: =J6+L6 -> 1722.798 | N6: 0.2 | O6: =$M6/(1-N6) -> 2153.4975 | P6: =MROUND(O6,10) -> 2150
A7: CC BLACK & CHROME PLATE | B7: BS-PL-03 | C7: PUSH PLATE FOR CONCEALED CISTERN | E7: 1170 | F7: 0.05 | G7: 0.13 | H7: =E7*F7 -> 58.5 | I7: =(E7+H7)*G7 -> 159.705 | J7: =E7+H7+I7 -> 1388.205 | K7: 0.2 | L7: =J7*K7 -> 277.641 | M7: =J7+L7 -> 1665.846 | N7: 0.2 | O7: =$M7/(1-N7) -> 2082.3075 | P7: =MROUND(O7,10) -> 2080
A8: CC MATT BLACK PLATE | B8: BS-MB-01 | C8: PUSH PLATE FOR CONCEALED CISTERN | E8: 2240 | F8: 0.05 | G8: 0.13 | H8: =E8*F8 -> 112 | I8: =(E8+H8)*G8 -> 305.76 | J8: =E8+H8+I8 -> 2657.76 | K8: 0.15 | L8: 398.664 | M8: 3056.424 | N8: 0.2 | O8: 3820.53 | P8: =MROUND(O8,10) -> 3820
A9: ONE PIECE COMMODE
A10: PV One piece C 29 W S Trap | B10: OP-29-S | C10: ONE PIECE CLOSET | D10: INVICTUS | E10: 18550 | F10: 0 | G10: 0.13 | H10: 0 | I10: 2411.5 | J10: 20961.5 | K10: 0.2 | L10: =J10*K10 -> 4192.3 | M10: =J10+L10 -> 25153.8 | N10: 0.2 | O10: =$M10/(1-N10) -> 31442.25 | P10: =MROUND(O10,10) -> 31440
A11: UB One piece C 32 W S Trap | B11: OP-32-S | C11: ONE PIECE CLOSET | D11: DEON | E11: 12840 | F11: 0 | G11: 0.13 | H11: 0 | I11: 1669.2 | J11: 14509.2 | K11: 0.2 | L11: =J11*K11 -> 2901.84 | M11: =J11+L11 -> 17411.04 | N11: 0.2 | O11: =$M11/(1-N11) -> 21763.8 | P11: =MROUND(O11,10) -> 21760
A12: UB One piece C 37 W S Trap | B12: OP-37-S | C12: ONE PIECE CLOSET | D12: Colossus | E12: 19140 | F12: 0 | G12: 0.13 | H12: 0 | I12: 2488.2 | J12: 21628.2 | K12: 0.2 | L12: =J12*K12 -> 4325.64 | M12: =J12+L12 -> 25953.84 | N12: 0.2 | O12: =$M12/(1-N12) -> 32442.3 | P12: =MROUND(O12,10) -> 32440
A13: UJ One piece 92 W S Trap | B13: OP-92-S | C13: ONE PIECE CLOSET | D13: MAXIMUS | E13: 19330 | F13: 0 | G13: 0.13 | H13: 0 | I13: 2512.9 | J13: 21842.9 | K13: 0.2 | L13: =J13*K13 -> 4368.58 | M13: =J13+L13 -> 26211.48 | N13: 0.2 | O13: =$M13/(1-N13) -> 32764.35 | P13: =MROUND(O13,10) -> 32760
A14: YD One piece C 39 W S Trap | B14: OP-39-S | C14: ONE PIECE CLOSET | D14: Proton | E14: 13640 | F14: 0 | G14: 0.13 | H14: 0 | I14: 1773.2 | J14: 15413.2 | K14: 0.2 | L14: =J14*K14 -> 3082.64 | M14: =J14+L14 -> 18495.84 | N14: 0.2 | O14: =$M14/(1-N14) -> 23119.8 | P14: =MROUND(O14,10) -> 23120
A15: YD One piece C 53 W S Trap | B15: OP-53-S | C15: ONE PIECE CLOSET | D15: Infinite | E15: 14910 | F15: 0 | G15: 0.13 | H15: 0 | I15: 1938.3 | J15: 16848.3 | K15: 0.2 | L15: =J15*K15 -> 3369.66 | M15: =J15+L15 -> 20217.96 | N15: 0.2 | O15: =$M15/(1-N15) -> 25272.45 | P15: =MROUND(O15,10) -> 25270
A16: YD One piece C 55 W S Trap | B16: OP-55-S | C16: ONE PIECE CLOSET | D16: Proton | E16: 13170 | F16: 0 | G16: 0.13 | H16: 0 | I16: 1712.1 | J16: 14882.1 | K16: 0.2 | L16: =J16*K16 -> 2976.42 | M16: =J16+L16 -> 17858.52 | N16: 0.2 | O16: =$M16/(1-N16) -> 22323.15 | P16: =MROUND(O16,10) -> 22320
A17: YD One piece C 56 W S Trap | B17: OP-56-S | C17: ONE PIECE CLOSET | D17: Trend | E17: 10330 | F17: 0 | G17: 0.13 | H17: 0 | I17: 1342.9 | J17: 11672.9 | K17: 0.2 | L17: =J17*K17 -> 2334.58 | M17: =J17+L17 -> 14007.48 | N17: 0.2 | O17: =$M17/(1-N17) -> 17509.35 | P17: =MROUND(O17,10) -> 17510
A18: UJ One piece C 29 W S Trap | B18: OP-29-SN | C18: ONE PIECE CLOSET | D18: PROTON | E18: 18750 | F18: 0 | G18: 0.13 | H18: 0 | I18: 2437.5 | J18: 21187.5 | K18: 0.2 | L18: =J18*K18 -> 4237.5 | M18: =J18+L18 -> 25425 | N18: 0.2 | O18: =$M18/(1-N18) -> 31781.25 | P18: =MROUND(O18,10) -> 31780
A19: YD One piece C 57 W S Trap | B19: OP-57-S | C19: ONE PIECE CLOSET | E19: 13190 | F19: 0 | G19: 0.13 | H19: 0 | I19: 1714.7 | J19: 14904.7 | K19: 0.2 | L19: =J19*K19 -> 2980.94 | M19: =J19+L19 -> 17885.64 | N19: 0.2 | O19: =$M19/(1-N19) -> 22357.05 | P19: =MROUND(O19,10) -> 22360
A20: YD One piece C 58 W S Trap | B20: OP-58-S | C20: ONE PIECE CLOSET | E20: 15440 | F20: 0 | G20: 0.13 | H20: 0 | I20: 2007.2 | J20: 17447.2 | K20: 0.2 | L20: =J20*K20 -> 3489.44 | M20: =J20+L20 -> 20936.64 | N20: 0.2 | O20: =$M20/(1-N20) -> 26170.8 | P20: =MROUND(O20,10) -> 26170
A21: WALL HUNG COMMODE
A22: BF Wall Hung C 32 W P Trap | B22: WH-32-P | C22: WALL HUNG COMMODE | D22: Proton | E22: 9590 | F22: 0 | G22: 0.13 | H22: 0 | I22: 1246.7 | J22: 10836.7 | K22: 0.2 | L22: =J22*K22 -> 2167.34 | M22: =J22+L22 -> 13004.04 | N22: 0.2 | O22: =$M22/(1-N22) -> 16255.05 | P22: =MROUND(O22,10) -> 16260
A23: UB Wall Hung C 24 W P Trap | B23: WH-24-P | C23: WALL HUNG COMMODE | D23: MYSTIC | E23: 10390 | F23: 0 | G23: 0.13 | H23: 0 | I23: 1350.7 | J23: 11740.7 | K23: 0.2 | L23: =J23*K23 -> 2348.14 | M23: =J23+L23 -> 14088.84 | N23: 0.2 | O23: =$M23/(1-N23) -> 17611.05 | P23: =MROUND(O23,10) -> 17610
A24: UB Wall Hung C 29 W P Trap UF | B24: WH-29-UF | C24: WALL HUNG COMMODE | D24: Proton | E24: 13250 | F24: 0 | G24: 0.13 | H24: 0 | I24: 1722.5 | J24: 14972.5 | K24: 0.2 | L24: =J24*K24 -> 2994.5 | M24: =J24+L24 -> 17967 | N24: 0.2 | O24: =$M24/(1-N24) -> 22458.75 | P24: =MROUND(O24,10) -> 22460
A25: UJ Wall Hung 94 W P Trap | B25: WH-94-P | C25: WALL HUNG COMMODE | D25: ARTISAN | E25: 19680 | F25: 0 | G25: 0.13 | H25: 0 | I25: 2558.4 | J25: 22238.4 | K25: 0.2 | L25: =J25*K25 -> 4447.68 | M25: =J25+L25 -> 26686.08 | N25: 0.2 | O25: =$M25/(1-N25) -> 33357.6 | P25: =MROUND(O25,10) -> 33360
A26: UJ Wall Hung 95 W P Trap | B26: WH-95-P | C26: WALL HUNG COMMODE | D26: TIMELESS | E26: 19680 | F26: 0 | G26: 0.13 | H26: 0 | I26: 2558.4 | J26: 22238.4 | K26: 0.2 | L26: =J26*K26 -> 4447.68 | M26: =J26+L26 -> 26686.08 | N26: 0.2 | O26: =$M26/(1-N26) -> 33357.6 | P26: =MROUND(O26,10) -> 33360
A27: UJ Wall Hung 97 W P Trap | B27: WH-97-P | C27: WALL HUNG COMMODE | D27: ALTIUS | E27: 24080 | F27: 0 | G27: 0.13 | H27: 0 | I27: 3130.4 | J27: 27210.4 | K27: 0.2 | L27: =J27*K27 -> 5442.08 | M27: =J27+L27 -> 32652.48 | N27: 0.2 | O27: =$M27/(1-N27) -> 40815.6 | P27: =MROUND(O27,10) -> 40820
A28: YD Wall Hung C 19 W P Trap | B28: WH-19-P | C28: WALL HUNG COMMODE | D28: Primus | E28: 6110 | F28: 0 | G28: 0.13 | H28: 0 | I28: 794.3 | J28: 6904.3 | K28: 0.2 | L28: =J28*K28 -> 1380.86 | M28: =J28+L28 -> 8285.16 | N28: 0.2 | O28: =$M28/(1-N28) -> 10356.45 | P28: =MROUND(O28,10) -> 10360
A29: YD Wall Hung C 27 W P Trap | B29: WH-27-P | C29: WALL HUNG COMMODE | D29: MAXIMUS | E29: 15630 | F29: 0 | G29: 0.13 | H29: 0 | I29: 2031.9 | J29: 17661.9 | K29: 0.2 | L29: =J29*K29 -> 3532.38 | M29: =J29+L29 -> 21194.28 | N29: 0.2 | O29: =$M29/(1-N29) -> 26492.85 | P29: =MROUND(O29,10) -> 26490
A30: YD Wall Hung C 31 W P Trap | B30: WH-31-P | C30: WALL HUNG COMMODE | D30: Mystic | E30: 10280 | F30: 0 | G30: 0.13 | H30: 0 | I30: 1336.4 | J30: 11616.4 | K30: 0.2 | L30: =J30*K30 -> 2323.28 | M30: =J30+L30 -> 13939.68 | N30: 0.2 | O30: =$M30/(1-N30) -> 17424.6 | P30: =MROUND(O30,10) -> 17420
A31: YD Wall Hung C 35 W P Trap | B31: WH-35-P | C31: WALL HUNG COMMODE | D31: Colossus | E31: 12060 | F31: 0 | G31: 0.13 | H31: 0 | I31: 1567.8 | J31: 13627.8 | K31: 0.2 | L31: =J31*K31 -> 2725.56 | M31: =J31+L31 -> 16353.36 | N31: 0.2 | O31: =$M31/(1-N31) -> 20441.7 | P31: =MROUND(O31,10) -> 20440
A32: YD Wall Hung C 36 W P Trap | B32: WH-36-P | C32: WALL HUNG COMMODE | D32: Invictus | E32: 14800 | F32: 0 | G32: 0.13 | H32: 0 | I32: 1924 | J32: 16724 | K32: 0.2 | L32: =J32*K32 -> 3344.8 | M32: =J32+L32 -> 20068.8 | N32: 0.2 | O32: =$M32/(1-N32) -> 25086 | P32: =MROUND(O32,10) -> 25090
A33: CANVAS
A34: JJ Wall Hung 70 B P Trap | B34: WH-70-BLK | C34: WALL HUNG COMMODE | D34: Canvas | E34: 52040 | F34: 0 | G34: 0.13 | H34: 0 | I34: 6765.2 | J34: 58805.2 | K34: 0.2 | L34: =J34*K34 -> 11761.04 | M34: =J34+L34 -> 70566.24 | N34: 0.2 | O34: =$M34/(1-N34) -> 88207.8 | P34: =MROUND(O34,10) -> 88210
A35: JJ Wall Hung 90 B P Trap | B35: WH-90-BLK | C35: WALL HUNG COMMODE | D35: Colossus | E35: 31200 | F35: 0 | G35: 0.13 | H35: 0 | I35: 4056 | J35: 35256 | K35: 0.2 | L35: =J35*K35 -> 7051.2 | M35: =J35+L35 -> 42307.2 | N35: 0.2 | O35: =$M35/(1-N35) -> 52884 | P35: =MROUND(O35,10) -> 52880
A36: JJ Wall Hung 91 B P Trap | B36: WH-91-BLK | C36: WALL HUNG COMMODE | D36: Evania | E36: 29680 | F36: 0 | G36: 0.13 | H36: 0 | I36: 3858.4 | J36: 33538.4 | K36: 0.2 | L36: =J36*K36 -> 6707.68 | M36: =J36+L36 -> 40246.08 | N36: 0.2 | O36: =$M36/(1-N36) -> 50307.6 | P36: =MROUND(O36,10) -> 50310
A37: JJ Wall Hung 92 B P Trap | B37: WH-92-BLK | C37: WALL HUNG COMMODE | D37: Serene | E37: 29760 | F37: 0 | G37: 0.13 | H37: 0 | I37: 3868.8 | J37: 33628.8 | K37: 0.2 | L37: =J37*K37 -> 6725.76 | M37: =J37+L37 -> 40354.56 | N37: 0.2 | O37: =$M37/(1-N37) -> 50443.2 | P37: =MROUND(O37,10) -> 50440
A38: JJ Wall Hung 70 G P Trap | B38: WH-70-GRE | C38: WALL HUNG COMMODE | D38: Canvas | E38: 54210 | F38: 0 | G38: 0.13 | H38: 0 | I38: 7047.3 | J38: 61257.3 | K38: 0.2 | L38: =J38*K38 -> 12251.46 | M38: =J38+L38 -> 73508.76 | N38: 0.2 | O38: =$M38/(1-N38) -> 91885.95 | P38: =MROUND(O38,10) -> 91890
A39: JJ Wall Hung 70 L P Trap | B39: WH-70-BGE | C39: WALL HUNG COMMODE | D39: Canvas | E39: 54210 | F39: 0 | G39: 0.13 | H39: 0 | I39: 7047.3 | J39: 61257.3 | K39: 0.2 | L39: =J39*K39 -> 12251.46 | M39: =J39+L39 -> 73508.76 | N39: 0.2 | O39: =$M39/(1-N39) -> 91885.95 | P39: =MROUND(O39,10) -> 91890
A40: JJ Table Top 70 B | B40: TT-70-BLK | C40: TABLE TOP BASIN CANVAS | D40: Canvas | E40: 14750 | F40: 0 | G40: 0.13 | H40: 0 | I40: 1917.5 | J40: 16667.5 | K40: 0.2 | L40: =J40*K40 -> 3333.5 | M40: =J40+L40 -> 20001 | N40: 0.2 | O40: =$M40/(1-N40) -> 25001.25 | P40: =MROUND(O40,10) -> 25000
A41: JJ Table Top 72 B | B41: TT-72-BLK | C41: TABLE TOP BASIN CANVAS | D41: Canvas | E41: 14750 | F41: 0 | G41: 0.13 | H41: 0 | I41: 1917.5 | J41: 16667.5 | K41: 0.2 | L41: =J41*K41 -> 3333.5 | M41: =J41+L41 -> 20001 | N41: 0.2 | O41: =$M41/(1-N41) -> 25001.25 | P41: =MROUND(O41,10) -> 25000
A42: JJ Table Top 73 B | B42: TT-73-BLK | C42: TABLE TOP BASIN CANVAS | D42: Canvas | E42: 18220 | F42: 0 | G42: 0.13 | H42: 0 | I42: 2368.6 | J42: 20588.6 | K42: 0.2 | L42: =J42*K42 -> 4117.72 | M42: =J42+L42 -> 24706.32 | N42: 0.2 | O42: =$M42/(1-N42) -> 30882.9 | P42: =MROUND(O42,10) -> 30880
A43: JJ Table Top 70 G | B43: TT-70-GRE | C43: TABLE TOP BASIN CANVAS | D43: Canvas | E43: 14750 | F43: 0 | G43: 0.13 | H43: 0 | I43: 1917.5 | J43: 16667.5 | K43: 0.2 | L43: =J43*K43 -> 3333.5 | M43: =J43+L43 -> 20001 | N43: 0.2 | O43: =$M43/(1-N43) -> 25001.25 | P43: =MROUND(O43,10) -> 25000
A44: JJ Table Top 72 G | B44: TT-72-GRE | C44: TABLE TOP BASIN CANVAS | D44: Canvas | E44: 14750 | F44: 0 | G44: 0.13 | H44: 0 | I44: 1917.5 | J44: 16667.5 | K44: 0.2 | L44: =J44*K44 -> 3333.5 | M44: =J44+L44 -> 20001 | N44: 0.2 | O44: =$M44/(1-N44) -> 25001.25 | P44: =MROUND(O44,10) -> 25000
A45: JJ Table Top 73 G | B45: TT-73-GRE | C45: TABLE TOP BASIN CANVAS | D45: Canvas | E45: 18220 | F45: 0 | G45: 0.13 | H45: 0 | I45: 2368.6 | J45: 20588.6 | K45: 0.2 | L45: =J45*K45 -> 4117.72 | M45: =J45+L45 -> 24706.32 | N45: 0.2 | O45: =$M45/(1-N45) -> 30882.9 | P45: =MROUND(O45,10) -> 30880
... A48: JJ Table Top 73 L | B48: TT-73-BGE | C48: TABLE TOP BASIN CANVAS | D48: Canvas | E48: 18220 | F48: 0 | G48: 0.13 | H48: 0 | I48: 2368.6 | J48: 20588.6 | K48: 0.2 | L48: =J48*K48 -> 4117.72 | M48: =J48+L48 -> 24706.32 | N48: 0.2 | O48: =$M48/(1-N48) -> 30882.9 | P48: =MROUND(O48,10) -> 30880
A49: URINALS
A50: BP SNU CONCEALED SENSOR - URINAL | B50: SNU-25-X | C50: URINAL SENSOR | D50: Timless | E50: 12020 | F50: 0 | G50: 0.13 | H50: 0 | I50: 1562.6 | J50: 13582.6 | K50: 0.2 | L50: =J50*K50 -> 2716.52 | M50: =J50+L50 -> 16299.12 | N50: 0.2 | O50: =$M50/(1-N50) -> 20373.9 | P50: =MROUND(O50,10) -> 20370
A51: UB SENSOR URINAL 24 W MEDIUM | B51: URS-24-M | C51: URINAL | D51: Proton UR | E51: 16470 | F51: 0 | G51: 0.13 | H51: 0 | I51: 2141.1 | J51: 18611.1 | K51: 0.2 | L51: =J51*K51 -> 3722.22 | M51: =J51+L51 -> 22333.32 | N51: 0.2 | O51: =$M51/(1-N51) -> 27916.65 | P51: =MROUND(O51,10) -> 27920
A52: PV URINAL U 22 W MEDIUM | B52: UR-22-M | C52: URINAL | D52: Contemporary | E52: 3580 | F52: 0 | G52: 0.13 | H52: 0 | I52: 465.4 | J52: 4045.4 | K52: 0.2 | L52: =J52*K52 -> 809.08 | M52: =J52+L52 -> 4854.48 | N52: 0.2 | O52: =$M52/(1-N52) -> 6068.1 | P52: =MROUND(O52,10) -> 6070
A53: ST URINAL U 22 W MEDIUM | B53: UR-22-MS | C53: URINAL | D53: CONTEMPORARY UR | E53: 3580 | F53: 0 | G53: 0.13 | H53: 0 | I53: 465.4 | J53: 4045.4 | K53: 0.2 | L53: =J53*K53 -> 809.08 | M53: =J53+L53 -> 4854.48 | N53: 0.2 | O53: =$M53/(1-N53) -> 6068.1 | P53: =MROUND(O53,10) -> 6070
A54: UB URINAL U 21 LS LARGE | B54: UR-21-LS | C54: URINAL | D54: DEON URS | E54: 5070 | F54: 0 | G54: 0.13 | H54: 0 | I54: 659.1 | J54: 5729.1 | K54: 0.2 | L54: =J54*K54 -> 1145.82 | M54: =J54+L54 -> 6874.92 | N54: 0.2 | O54: =$M54/(1-N54) -> 8593.65 | P54: =MROUND(O54,10) -> 8590
A55: UB URINAL U 21 W SMALL | B55: UR-21-S | C55: URINAL | D55: TREND UR | E55: 2540 | F55: 0 | G55: 0.13 | H55: 0 | I55: 330.2 | J55: 2870.2 | K55: 0.2 | L55: =J55*K55 -> 574.04 | M55: =J55+L55 -> 3444.24 | N55: 0.2 | O55: =$M55/(1-N55) -> 4305.3 | P55: =MROUND(O55,10) -> 4310
A56: YD URINAL U 21 W LARGE | B56: UR-21-L | C56: URINAL | D56: DEON UR | E56: 4320 | F56: 0 | G56: 0.13 | H56: 0 | I56: 561.6 | J56: 4881.6 | K56: 0.2 | L56: =J56*K56 -> 976.32 | M56: =J56+L56 -> 5857.92 | N56: 0.2 | O56: =$M56/(1-N56) -> 7322.4 | P56: =MROUND(O56,10) -> 7320
A57: WALL HUNG BASIN & FULL PEDESTAL
A58: PV Wall Hung B 21 W | B58: WM-21-X | C58: WALL HUNG BASIN | D58: TIMELESS | E58: 2810 | F58: 0 | G58: 0.13 | H58: 0 | I58: 365.3 | J58: 3175.3 | K58: 0.2 | L58: =J58*K58 -> 635.06 | M58: =J58+L58 -> 3810.36 | N58: 0.2 | O58: =$M58/(1-N58) -> 4762.95 | P58: =MROUND(O58,10) -> 4760
A59: PV Wall Hung B 27 W | B59: WM-27-X | C59: WALL HUNG BASIN | D59: DEON | E59: 2360 | F59: 0 | G59: 0.13 | H59: 0 | I59: 306.8 | J59: 2666.8 | K59: 0.2 | L59: =J59*K59 -> 533.36 | M59: =J59+L59 -> 3200.16 | N59: 0.2 | O59: =$M59/(1-N59) -> 4000.2 | P59: =MROUND(O59,10) -> 4000 | S59: \
A60: UB Wall Hung B 28 W | B60: WM-28-X | C60: WALL HUNG BASIN | D60: CONTEMPORARY | E60: 2500 | F60: 0 | G60: 0.13 | H60: 0 | I60: 325 | J60: 2825 | K60: 0.2 | L60: =J60*K60 -> 565 | M60: =J60+L60 -> 3390 | N60: 0.2 | O60: =$M60/(1-N60) -> 4237.5 | P60: =MROUND(O60,10) -> 4240
A61: YD Wall Hung B 31 W | B61: WM-31-X | C61: WALL HUNG BASIN | D61: Proton | E61: 2370 | F61: 0 | G61: 0.13 | H61: 0 | I61: 308.1 | J61: 2678.1 | K61: 0.2 | L61: =J61*K61 -> 535.62 | M61: =J61+L61 -> 3213.72 | N61: 0.2 | O61: =$M61/(1-N61) -> 4017.15 | P61: =MROUND(O61,10) -> 4020
A62: PV Full Pedestal P 23 W | B62: FP-23-X | C62: FULL PEDESTAL | D62: SERENE | E62: 2730 | F62: 0 | G62: 0.13 | H62: 0 | I62: 354.9 | J62: 3084.9 | K62: 0.2 | L62: =J62*K62 -> 616.98 | M62: =J62+L62 -> 3701.88 | N62: 0.2 | O62: =$M62/(1-N62) -> 4627.35 | P62: =MROUND(O62,10) -> 4630
A63: UB Full Pedestal P 28 W | B63: FP-28-X | C63: FULL PEDESTAL | D63: CONTEMPORARY | E63: 2290 | F63: 0 | G63: 0.13 | H63: 0 | I63: 297.7 | J63: 2587.7 | K63: 0.2 | L63: =J63*K63 -> 517.54 | M63: =J63+L63 -> 3105.24 | N63: 0.2 | O63: =$M63/(1-N63) -> 3881.55 | P63: =MROUND(O63,10) -> 3880
A64: YD Wall Hung B 29 W | B64: WM-29-X | C64: WALL HUNG BASIN | E64: 1970 | F64: 0 | G64: 0.13 | H64: 0 | I64: 256.1 | J64: 2226.1 | K64: 0.2 | L64: =J64*K64 -> 445.22 | M64: =J64+L64 -> 2671.32 | N64: 0.2 | O64: =$M64/(1-N64) -> 3339.15 | P64: =MROUND(O64,10) -> 3340
A65: PV Full Pedestal S 23 W | B65: FP-23-S | C65: FULL PEDESTAL | D65: SERENE | E65: 2730 | F65: 0 | G65: 0.13 | H65: 0 | I65: 354.9 | J65: 3084.9 | K65: 0.2 | L65: =J65*K65 -> 616.98 | M65: =J65+L65 -> 3701.88 | N65: 0.2 | O65: =$M65/(1-N65) -> 4627.35 | P65: =MROUND(O65,10) -> 4630
A66: YD Full Pedestal X 29 W | B66: FP-29-X | C66: FULL PEDESTAL | E66: 1990 | F66: 0 | G66: 0.13 | H66: 0 | I66: 258.7 | J66: 2248.7 | K66: 0.2 | L66: =J66*K66 -> 449.74 | M66: =J66+L66 -> 2698.44 | N66: 0.2 | O66: =$M66/(1-N66) -> 3373.05 | P66: =MROUND(O66,10) -> 3370
A67: TABLE TOP BASIN
A68: HC Table Top 33 W | B68: TT-33-X | C68: TABLE TOP BASIN | D68: MYSTIC | E68: 7590 | F68: 0 | G68: 0.13 | H68: 0 | I68: 986.7 | J68: 8576.7 | K68: 0.2 | L68: =J68*K68 -> 1715.34 | M68: =J68+L68 -> 10292.04 | N68: 0.2 | O68: =$M68/(1-N68) -> 12865.05 | P68: =MROUND(O68,10) -> 12870
A69: PV Table Top 32 W | B69: TT-32-X | C69: TABLE TOP BASIN | D69: ARTISAN D | E69: 7570 | F69: 0 | G69: 0.13 | H69: 0 | I69: 984.1 | J69: 8554.1 | K69: 0.2 | L69: =J69*K69 -> 1710.82 | M69: =J69+L69 -> 10264.92 | N69: 0.2 | O69: =$M69/(1-N69) -> 12831.15 | P69: =MROUND(O69,10) -> 12830
A70: ST Table Top 34 W | B70: TT-34-X | C70: TABLE TOP BASIN | D70: Maximus | E70: 6100 | F70: 0 | G70: 0.13 | H70: 0 | I70: 793 | J70: 6893 | K70: 0.2 | L70: =J70*K70 -> 1378.6 | M70: =J70+L70 -> 8271.6 | N70: 0.2 | O70: =$M70/(1-N70) -> 10339.5 | P70: =MROUND(O70,10) -> 10340
A71: UB Table Top B 25 W | B71: TT-25-X | C71: TABLE TOP BASIN | D71: EVANIA | E71: 4320 | F71: 0 | G71: 0.13 | H71: 0 | I71: 561.6 | J71: 4881.6 | K71: 0.2 | L71: =J71*K71 -> 976.32 | M71: =J71+L71 -> 5857.92 | N71: 0.2 | O71: =$M71/(1-N71) -> 7322.4 | P71: =MROUND(O71,10) -> 7320
A72: UB Table Top B 30 W | B72: TT-30-X | C72: TABLE TOP BASIN | D72: Proton | E72: 2830 | F72: 0 | G72: 0.13 | H72: 0 | I72: 367.9 | J72: 3197.9 | K72: 0.2 | L72: =J72*K72 -> 639.58 | M72: =J72+L72 -> 3837.48 | N72: 0.2 | O72: =$M72/(1-N72) -> 4796.85 | P72: =MROUND(O72,10) -> 4800
A73: UJ Table Top 43 W | B73: TT-43-X | C73: TABLE TOP BASIN | D73: MYSTIC | E73: 7570 | F73: 0 | G73: 0.13 | H73: 0 | I73: 984.1 | J73: 8554.1 | K73: 0.2 | L73: =J73*K73 -> 1710.82 | M73: =J73+L73 -> 10264.92 | N73: 0.2 | O73: =$M73/(1-N73) -> 12831.15 | P73: =MROUND(O73,10) -> 12830
A74: YD Table Top B 22 W | B74: TT-22-X | C74: TABLE TOP BASIN | D74: DEON | E74: 5460 | F74: 0 | G74: 0.13 | H74: 0 | I74: 709.8 | J74: 6169.8 | K74: 0.2 | L74: =J74*K74 -> 1233.96 | M74: =J74+L74 -> 7403.76 | N74: 0.2 | O74: =$M74/(1-N74) -> 9254.7 | P74: =MROUND(O74,10) -> 9250
A75: YD Table Top B 23 W | B75: TT-23-X | C75: TABLE TOP BASIN | D75: CONTEMPORARY | E75: 4260 | F75: 0 | G75: 0.13 | H75: 0 | I75: 553.8 | J75: 4813.8 | K75: 0.2 | L75: =J75*K75 -> 962.76 | M75: =J75+L75 -> 5776.56 | N75: 0.2 | O75: =$M75/(1-N75) -> 7220.7 | P75: =MROUND(O75,10) -> 7220
A76: OVER COUNTER BASIN
A77: DS OC C 21 W X Trap | B77: OC-21-X | C77: OVER COUNTER BASIN | D77: ALTIUS | E77: 8830 | F77: 0 | G77: 0.13 | H77: 0 | I77: 1147.9 | J77: 9977.9 | K77: 0.2 | L77: =J77*K77 -> 1995.58 | M77: =J77+L77 -> 11973.48 | N77: 0.2 | O77: =$M77/(1-N77) -> 14966.85 | P77: =MROUND(O77,10) -> 14970
A78: DS OC C 22 W X Trap | B78: OC-22-X | C78: OVER COUNTER BASIN | D78: MAXIMUS | E78: 12050 | F78: 0 | G78: 0.13 | H78: 0 | I78: 1566.5 | J78: 13616.5 | K78: 0.2 | L78: =J78*K78 -> 2723.3 | M78: =J78+L78 -> 16339.8 | N78: 0.2 | O78: =$M78/(1-N78) -> 20424.75 | P78: =MROUND(O78,10) -> 20420
A79: UNDER COUNTER BASIN
A80: YD Under counter B 22 W | B80: UC-22-X | C80: UNDER COUNTER BASIN | D80: DEON | E80: 2840 | F80: 0 | G80: 0.13 | H80: 0 | I80: 369.2 | J80: 3209.2 | K80: 0.2 | L80: =J80*K80 -> 641.84 | M80: =J80+L80 -> 3851.04 | N80: 0.2 | O80: =$M80/(1-N80) -> 4813.8 | P80: =MROUND(O80,10) -> 4810
A81: YD Under counter B 24 W | B81: UC-24-X | C81: UNDER COUNTER BASIN | D81: Proton | E81: 3190 | F81: 0 | G81: 0.13 | H81: 0 | I81: 414.7 | J81: 3604.7 | K81: 0.2 | L81: =J81*K81 -> 720.94 | M81: =J81+L81 -> 4325.64 | N81: 0.2 | O81: =$M81/(1-N81) -> 5407.05 | P81: =MROUND(O81,10) -> 5410
A82: INTEGRETED BASIN
A83: UB Integrated B 21 W | B83: IC-21-X | C83: INTEGRETED BASIN | D83: SERENE | E83: 8490 | F83: 0 | G83: 0.13 | H83: 0 | I83: 1103.7 | J83: 9593.7 | K83: 0.2 | L83: =J83*K83 -> 1918.74 | M83: =J83+L83 -> 11512.44 | N83: 0.2 | O83: =$M83/(1-N83) -> 14390.55 | P83: =MROUND(O83,10) -> 14390
A84: UB Integrated B 22 W | B84: IC-22-X | C84: INTEGRETED BASIN | D84: ARTISAN | E84: 9080 | F84: 0 | G84: 0.13 | H84: 0 | I84: 1180.4 | J84: 10260.4 | K84: 0.2 | L84: =J84*K84 -> 2052.08 | M84: =J84+L84 -> 12312.48 | N84: 0.2 | O84: =$M84/(1-N84) -> 15390.6 | P84: =MROUND(O84,10) -> 15390

Sheet Sheet25

Sheet Sheet26

Sheet Sheet27

Sheet Sheet28

Sheet Sheet29

Sheet Sheet30

Sheet Sheet31

Sheet Sheet32

Sheet Sheet33

Sheet BATHSENSE
B1: Material Desc | C1: Lower limit | D1: CP | E1: New Price | F1: Excise % | G1: Vat % | H1: Excise amt. | I1: Vat amt. | J1: Final DP With Excise & Vat | K1: Dealer Margin | L1: Dealer Margin | M1: Total Price | N1: Customer Discount | O1: Round Up | P1: Final MRP | Q1: Discount
B2: CANVAS
B3: FRENCH GOLD
B4: ANGLE COCK WITH WF French Gold | C4: GDALAC101 | D4: CANVAS | E4: 3240 | F4: 0.05 | G4: 0.13 | H4: =F4*E4 -> 162 | I4: =G4*(E4+H4) -> 442.26 | J4: =E4+H4+I4 -> 3844.26 | K4: 0.2 | L4: =J4*K4 -> 768.852 | M4: =J4+L4 -> 4613.112 | N4: 0.2 | O4: =$M4/(1-N4) -> 5766.39 | P4: =MROUND(O4,10) -> 5770
B5: BIB COCK WITH WF French Gold | C5: GDALBC101 | D5: CANVAS | E5: 4520 | F5: 0.05 | G5: 0.13 | H5: =F5*E5 -> 226 | I5: =G5*(E5+H5) -> 616.98 | J5: =E5+H5+I5 -> 5362.98 | K5: 0.2 | L5: =J5*K5 -> 1072.596 | M5: =J5+L5 -> 6435.576 | N5: 0.2 | O5: =$M5/(1-N5) -> 8044.47 | P5: =MROUND(O5,10) -> 8040
B6: BIB COCK 2-IN-1 WITH WF French Gold | C6: GDALBC102 | D6: CANVAS | E6: 5460 | F6: 0.05 | G6: 0.13 | H6: =F6*E6 -> 273 | I6: =G6*(E6+H6) -> 745.29 | J6: =E6+H6+I6 -> 6478.29 | K6: 0.2 | L6: =J6*K6 -> 1295.658 | M6: =J6+L6 -> 7773.948 | N6: 0.2 | O6: =$M6/(1-N6) -> 9717.435 | P6: =MROUND(O6,10) -> 9720
B7: SLBM W/O PWS French Gold | C7: GDALBM101 | D7: CANVAS | E7: 10600 | F7: 0.05 | G7: 0.13 | H7: =F7*E7 -> 530 | I7: =G7*(E7+H7) -> 1446.9 | J7: =E7+H7+I7 -> 12576.9 | K7: 0.2 | L7: =J7*K7 -> 2515.38 | M7: =J7+L7 -> 15092.28 | N7: 0.2 | O7: =$M7/(1-N7) -> 18865.35 | P7: =MROUND(O7,10) -> 18870
B8: SLBM EXTENDED French Gold | C8: GDALBM102 | D8: CANVAS | E8: 14170 | F8: 0.05 | G8: 0.13 | H8: =F8*E8 -> 708.5 | I8: =G8*(E8+H8) -> 1934.205 | J8: =E8+H8+I8 -> 16812.705 | K8: 0.2 | L8: =J8*K8 -> 3362.541 | M8: =J8+L8 -> 20175.246 | N8: 0.2 | O8: =$M8/(1-N8) -> 25219.058 | P8: =MROUND(O8,10) -> 25220
B9: UPPER SLCD FOR BASIN SPOUT French Gold | C9: GDALDV103U | D9: CANVAS | E9: 9040 | F9: 0.05 | G9: 0.13 | H9: =F9*E9 -> 452 | I9: =G9*(E9+H9) -> 1233.96 | J9: =E9+H9+I9 -> 10725.96 | K9: 0.2 | L9: =J9*K9 -> 2145.192 | M9: =J9+L9 -> 12871.152 | N9: 0.2 | O9: =$M9/(1-N9) -> 16088.94 | P9: =MROUND(O9,10) -> 16090
B10: UPPER SLCD HF PUSH French Gold | C10: GDALDV111U | D10: CANVAS | E10: 4360 | F10: 0.05 | G10: 0.13 | H10: =F10*E10 -> 218 | I10: =G10*(E10+H10) -> 595.14 | J10: =E10+H10+I10 -> 5173.14 | K10: 0.2 | L10: =J10*K10 -> 1034.628 | M10: =J10+L10 -> 6207.768 | N10: 0.2 | O10: =$M10/(1-N10) -> 7759.71 | P10: =MROUND(O10,10) -> 7760
B11: BT PLAIN SPOUT French Gold | C11: GDALSP101 | D11: CANVAS | E11: 3640 | F11: 0.05 | G11: 0.13 | H11: =F11*E11 -> 182 | I11: =G11*(E11+H11) -> 496.86 | J11: =E11+H11+I11 -> 4318.86 | K11: 0.2 | L11: =J11*K11 -> 863.772 | M11: =J11+L11 -> 5182.632 | N11: 0.2 | O11: =$M11/(1-N11) -> 6478.29 | P11: =MROUND(O11,10) -> 6480
B12: BODY SLCD B. SPOUT NEW (CASTED) French G | C12: GDB2BD101 | D12: CANVAS | E12: 6880 | F12: 0.05 | G12: 0.13 | H12: =F12*E12 -> 344 | I12: =G12*(E12+H12) -> 939.12 | J12: =E12+H12+I12 -> 8163.12 | K12: 0.2 | L12: =J12*K12 -> 1632.624 | M12: =J12+L12 -> 9795.744 | N12: 0.2 | O12: =$M12/(1-N12) -> 12244.68 | P12: =MROUND(O12,10) -> 12240
B13: BODY ROYALE INSPIRE SLCD HF French Gold | C13: GDB2DV202 | D13: CANVAS | E13: 8900 | F13: 0.05 | G13: 0.13 | H13: =F13*E13 -> 445 | I13: =G13*(E13+H13) -> 1214.85 | J13: =E13+H13+I13 -> 10559.85 | K13: 0.2 | L13: =J13*K13 -> 2111.97 | M13: =J13+L13 -> 12671.82 | N13: 0.2 | O13: =$M13/(1-N13) -> 15839.775 | P13: =MROUND(O13,10) -> 15840
B14: 9 inch OHS Round French Gold | C14: GDBHRF101 | D14: CANVAS | E14: 7040 | F14: 0.05 | G14: 0.13 | H14: =F14*E14 -> 352 | I14: =G14*(E14+H14) -> 960.96 | J14: =E14+H14+I14 -> 8352.96 | K14: 0.2 | L14: =J14*K14 -> 1670.592 | M14: =J14+L14 -> 10023.552 | N14: 0.2 | O14: =$M14/(1-N14) -> 12529.44 | P14: =MROUND(O14,10) -> 12530
B15: 9 inch OHS Square French Gold | C15: GDBHRF102 | D15: CANVAS | E15: 9780 | F15: 0.05 | G15: 0.13 | H15: =F15*E15 -> 489 | I15: =G15*(E15+H15) -> 1334.97 | J15: =E15+H15+I15 -> 11603.97 | K15: 0.2 | L15: =J15*K15 -> 2320.794 | M15: =J15+L15 -> 13924.764 | N15: 0.2 | O15: =$M15/(1-N15) -> 17405.955 | P15: =MROUND(O15,10) -> 17410
... B27: 18" RFS arm round New French Gold | C27: GDSA107N | D27: CANVAS | E27: 4420 | F27: 0.05 | G27: 0.13 | H27: =F27*E27 -> 221 | I27: =G27*(E27+H27) -> 603.33 | J27: =E27+H27+I27 -> 5244.33 | K27: 0.2 | L27: =J27*K27 -> 1048.866 | M27: =J27+L27 -> 6293.196 | N27: 0.2 | O27: =$M27/(1-N27) -> 7866.495 | P27: =MROUND(O27,10) -> 7870
B28: MAT BLACK
B29: ANGLE COCK WITH WF Black | C29: MBALAC101 | D29: CANVAS | E29: 3810 | F29: 0.05 | G29: 0.13 | H29: =F29*E29 -> 190.5 | I29: =G29*(E29+H29) -> 520.065 | J29: =E29+H29+I29 -> 4520.565 | K29: 0.2 | L29: =J29*K29 -> 904.113 | M29: =J29+L29 -> 5424.678 | N29: 0.2 | O29: =$M29/(1-N29) -> 6780.8475 | P29: =MROUND(O29,10) -> 6780
B30: BIB COCK WITH WF Black | C30: MBALBC101 | D30: CANVAS | E30: 5400 | F30: 0.05 | G30: 0.13 | H30: =F30*E30 -> 270 | I30: =G30*(E30+H30) -> 737.1 | J30: =E30+H30+I30 -> 6407.1 | K30: 0.2 | L30: =J30*K30 -> 1281.42 | M30: =J30+L30 -> 7688.52 | N30: 0.2 | O30: =$M30/(1-N30) -> 9610.65 | P30: =MROUND(O30,10) -> 9610
B31: BIB COCK 2-IN-1 WITH WF Black | C31: MBALBC102 | D31: CANVAS | E31: 6670 | F31: 0.05 | G31: 0.13 | H31: =F31*E31 -> 333.5 | I31: =G31*(E31+H31) -> 910.455 | J31: =E31+H31+I31 -> 7913.955 | K31: 0.2 | L31: =J31*K31 -> 1582.791 | M31: =J31+L31 -> 9496.746 | N31: 0.2 | O31: =$M31/(1-N31) -> 11870.932 | P31: =MROUND(O31,10) -> 11870
B32: SLBM W/O PWS Black | C32: MBALBM101 | D32: CANVAS | E32: 13640 | F32: 0.05 | G32: 0.13 | H32: =F32*E32 -> 682 | I32: =G32*(E32+H32) -> 1861.86 | J32: =E32+H32+I32 -> 16183.86 | K32: 0.2 | L32: =J32*K32 -> 3236.772 | M32: =J32+L32 -> 19420.632 | N32: 0.2 | O32: =$M32/(1-N32) -> 24275.79 | P32: =MROUND(O32,10) -> 24280
B33: SLBM EXTENDED Black | C33: MBALBM102 | D33: CANVAS | E33: 17130 | F33: 0.05 | G33: 0.13 | H33: =F33*E33 -> 856.5 | I33: =G33*(E33+H33) -> 2338.245 | J33: =E33+H33+I33 -> 20324.745 | K33: 0.2 | L33: =J33*K33 -> 4064.949 | M33: =J33+L33 -> 24389.694 | N33: 0.2 | O33: =$M33/(1-N33) -> 30487.117 | P33: =MROUND(O33,10) -> 30490
B34: UPPER SLCD FOR BASIN SPOUT Black | C34: MBALDV103U | D34: CANVAS | E34: 12750 | F34: 0.05 | G34: 0.13 | H34: =F34*E34 -> 637.5 | I34: =G34*(E34+H34) -> 1740.375 | J34: =E34+H34+I34 -> 15127.875 | K34: 0.2 | L34: =J34*K34 -> 3025.575 | M34: =J34+L34 -> 18153.45 | N34: 0.2 | O34: =$M34/(1-N34) -> 22691.812 | P34: =MROUND(O34,10) -> 22690
B35: UPPER SLCD HF PUSH Black | C35: MBALDV111U | D35: CANVAS | E35: 5400 | F35: 0.05 | G35: 0.13 | H35: =F35*E35 -> 270 | I35: =G35*(E35+H35) -> 737.1 | J35: =E35+H35+I35 -> 6407.1 | K35: 0.2 | L35: =J35*K35 -> 1281.42 | M35: =J35+L35 -> 7688.52 | N35: 0.2 | O35: =$M35/(1-N35) -> 9610.65 | P35: =MROUND(O35,10) -> 9610
B36: BT PLAIN SPOUT Black | C36: MBALSP101 | D36: CANVAS | E36: 4450 | F36: 0.05 | G36: 0.13 | H36: =F36*E36 -> 222.5 | I36: =G36*(E36+H36) -> 607.425 | J36: =E36+H36+I36 -> 5279.925 | K36: 0.2 | L36: =J36*K36 -> 1055.985 | M36: =J36+L36 -> 6335.91 | N36: 0.2 | O36: =$M36/(1-N36) -> 7919.8875 | P36: =MROUND(O36,10) -> 7920
B37: BUTTON SPOUT Black | C37: MBALSP102 | D37: CANVAS | E37: 5820 | F37: 0.05 | G37: 0.13 | H37: =F37*E37 -> 291 | I37: =G37*(E37+H37) -> 794.43 | J37: =E37+H37+I37 -> 6905.43 | K37: 0.2 | L37: =J37*K37 -> 1381.086 | M37: =J37+L37 -> 8286.516 | N37: 0.2 | O37: =$M37/(1-N37) -> 10358.145 | P37: =MROUND(O37,10) -> 10360
B38: BODY SLCD B. SPOUT NEW (CASTED) Black | C38: MBB2BD101 | D38: CANVAS | E38: 8570 | F38: 0.05 | G38: 0.13 | H38: =F38*E38 -> 428.5 | I38: =G38*(E38+H38) -> 1169.805 | J38: =E38+H38+I38 -> 10168.305 | K38: 0.2 | L38: =J38*K38 -> 2033.661 | M38: =J38+L38 -> 12201.966 | N38: 0.2 | O38: =$M38/(1-N38) -> 15252.458 | P38: =MROUND(O38,10) -> 15250
B39: BODY ROYALE INSPIRE SLCD HF Black | C39: MBB2DV202 | D39: CANVAS | E39: 9840 | F39: 0.05 | G39: 0.13 | H39: =F39*E39 -> 492 | I39: =G39*(E39+H39) -> 1343.16 | J39: =E39+H39+I39 -> 11675.16 | K39: 0.2 | L39: =J39*K39 -> 2335.032 | M39: =J39+L39 -> 14010.192 | N39: 0.2 | O39: =$M39/(1-N39) -> 17512.74 | P39: =MROUND(O39,10) -> 17510
B40: 9 inch OHS Round Matt Black | C40: MBBHRF101 | D40: CANVAS | E40: 9840 | F40: 0.05 | G40: 0.13 | H40: =F40*E40 -> 492 | I40: =G40*(E40+H40) -> 1343.16 | J40: =E40+H40+I40 -> 11675.16 | K40: 0.2 | L40: =J40*K40 -> 2335.032 | M40: =J40+L40 -> 14010.192 | N40: 0.2 | O40: =$M40/(1-N40) -> 17512.74 | P40: =MROUND(O40,10) -> 17510
... B55: 18" RFS arm round New Black | C55: MBSA107N | D55: CANVAS | E55: 5070 | F55: 0.05 | G55: 0.13 | H55: =F55*E55 -> 253.5 | I55: =G55*(E55+H55) -> 692.055 | J55: =E55+H55+I55 -> 6015.555 | K55: 0.2 | L55: =J55*K55 -> 1203.111 | M55: =J55+L55 -> 7218.666 | N55: 0.2 | O55: =$M55/(1-N55) -> 9023.3325 | P55: =MROUND(O55,10) -> 9020
B56: MAT RED
B57: ANGLE COCK WITH WF Red | C57: RDALAC101 | D57: CANVAS | E57: 3580 | F57: 0.05 | G57: 0.13 | H57: =F57*E57 -> 179 | I57: =G57*(E57+H57) -> 488.67 | J57: =E57+H57+I57 -> 4247.67 | K57: 0.2 | L57: =J57*K57 -> 849.534 | M57: =J57+L57 -> 5097.204 | N57: 0.2 | O57: =$M57/(1-N57) -> 6371.505 | P57: =MROUND(O57,10) -> 6370
B58: BIB COCK WITH WF Red | C58: RDALBC101 | D58: CANVAS | E58: 4990 | F58: 0.05 | G58: 0.13 | H58: =F58*E58 -> 249.5 | I58: =G58*(E58+H58) -> 681.135 | J58: =E58+H58+I58 -> 5920.635 | K58: 0.2 | L58: =J58*K58 -> 1184.127 | M58: =J58+L58 -> 7104.762 | N58: 0.2 | O58: =$M58/(1-N58) -> 8880.9525 | P58: =MROUND(O58,10) -> 8880
B59: BIB COCK 2-IN-1 WITH WF Red | C59: RDALBC102 | D59: CANVAS | E59: 6140 | F59: 0.05 | G59: 0.13 | H59: =F59*E59 -> 307 | I59: =G59*(E59+H59) -> 838.11 | J59: =E59+H59+I59 -> 7285.11 | K59: 0.2 | L59: =J59*K59 -> 1457.022 | M59: =J59+L59 -> 8742.132 | N59: 0.2 | O59: =$M59/(1-N59) -> 10927.665 | P59: =MROUND(O59,10) -> 10930
B60: SLBM W/O PWS Red | C60: RDALBM101 | D60: CANVAS | E60: 12140 | F60: 0.05 | G60: 0.13 | H60: =F60*E60 -> 607 | I60: =G60*(E60+H60) -> 1657.11 | J60: =E60+H60+I60 -> 14404.11 | K60: 0.2 | L60: =J60*K60 -> 2880.822 | M60: =J60+L60 -> 17284.932 | N60: 0.2 | O60: =$M60/(1-N60) -> 21606.165 | P60: =MROUND(O60,10) -> 21610
B61: SLBM EXTENDED Red | C61: RDALBM102 | D61: CANVAS | E61: 16180 | F61: 0.05 | G61: 0.13 | H61: =F61*E61 -> 809 | I61: =G61*(E61+H61) -> 2208.57 | J61: =E61+H61+I61 -> 19197.57 | K61: 0.2 | L61: =J61*K61 -> 3839.514 | M61: =J61+L61 -> 23037.084 | N61: 0.2 | O61: =$M61/(1-N61) -> 28796.355 | P61: =MROUND(O61,10) -> 28800
B62: UPPER SLCD FOR BASIN SPOUT Red | C62: RDALDV103U | D62: CANVAS | E62: 10790 | F62: 0.05 | G62: 0.13 | H62: =F62*E62 -> 539.5 | I62: =G62*(E62+H62) -> 1472.835 | J62: =E62+H62+I62 -> 12802.335 | K62: 0.2 | L62: =J62*K62 -> 2560.467 | M62: =J62+L62 -> 15362.802 | N62: 0.2 | O62: =$M62/(1-N62) -> 19203.502 | P62: =MROUND(O62,10) -> 19200
B63: UPPER SLCD HF PUSH Red | C63: RDALDV111U | D63: CANVAS | E63: 5400 | F63: 0.05 | G63: 0.13 | H63: =F63*E63 -> 270 | I63: =G63*(E63+H63) -> 737.1 | J63: =E63+H63+I63 -> 6407.1 | K63: 0.2 | L63: =J63*K63 -> 1281.42 | M63: =J63+L63 -> 7688.52 | N63: 0.2 | O63: =$M63/(1-N63) -> 9610.65 | P63: =MROUND(O63,10) -> 9610
B64: BT PLAIN SPOUT Red | C64: RDALSP101 | D64: CANVAS | E64: 4320 | F64: 0.05 | G64: 0.13 | H64: =F64*E64 -> 216 | I64: =G64*(E64+H64) -> 589.68 | J64: =E64+H64+I64 -> 5125.68 | K64: 0.2 | L64: =J64*K64 -> 1025.136 | M64: =J64+L64 -> 6150.816 | N64: 0.2 | O64: =$M64/(1-N64) -> 7688.52 | P64: =MROUND(O64,10) -> 7690
B65: BUTTON SPOUT Red | C65: RDALSP102 | D65: CANVAS | E65: 4750 | F65: 0.05 | G65: 0.13 | H65: =F65*E65 -> 237.5 | I65: =G65*(E65+H65) -> 648.375 | J65: =E65+H65+I65 -> 5635.875 | K65: 0.15 | L65: =J65*K65 -> 845.38125 | M65: =J65+L65 -> 6481.2563 | N65: 0.2 | O65: =$M65/(1-N65) -> 8101.5703 | P65: =MROUND(O65,10) -> 8100
B66: BODY SLCD B. SPOUT NEW (CASTED) Red | C66: RDB2BD101 | D66: CANVAS | E66: 7360 | F66: 0.05 | G66: 0.13 | H66: =F66*E66 -> 368 | I66: =G66*(E66+H66) -> 1004.64 | J66: =E66+H66+I66 -> 8732.64 | K66: 0.2 | L66: =J66*K66 -> 1746.528 | M66: =J66+L66 -> 10479.168 | N66: 0.2 | O66: =$M66/(1-N66) -> 13098.96 | P66: =MROUND(O66,10) -> 13100
B67: BODY ROYALE INSPIRE SLCD HF Red | C67: RDB2DV202 | D67: CANVAS | E67: 9840 | F67: 0.05 | G67: 0.13 | H67: =F67*E67 -> 492 | I67: =G67*(E67+H67) -> 1343.16 | J67: =E67+H67+I67 -> 11675.16 | K67: 0.2 | L67: =J67*K67 -> 2335.032 | M67: =J67+L67 -> 14010.192 | N67: 0.2 | O67: =$M67/(1-N67) -> 17512.74 | P67: =MROUND(O67,10) -> 17510
B68: ANGLE COCK WITH WF Red | C68: RDMYAC101 | D68: CANVAS | E68: 4320 | F68: 0.05 | G68: 0.13 | H68: =F68*E68 -> 216 | I68: =G68*(E68+H68) -> 589.68 | J68: =E68+H68+I68 -> 5125.68 | K68: 0.2 | L68: =J68*K68 -> 1025.136 | M68: =J68+L68 -> 6150.816 | N68: 0.2 | O68: =$M68/(1-N68) -> 7688.52 | P68: =MROUND(O68,10) -> 7690
... B75: BUTTON SPOUT Red | C75: RDMYSP102 | D75: CANVAS | E75: 7280 | F75: 0.05 | G75: 0.13 | H75: =F75*E75 -> 364 | I75: =G75*(E75+H75) -> 993.72 | J75: =E75+H75+I75 -> 8637.72 | K75: 0.2 | L75: =J75*K75 -> 1727.544 | M75: =J75+L75 -> 10365.264 | N75: 0.2 | O75: =$M75/(1-N75) -> 12956.58 | P75: =MROUND(O75,10) -> 12960
B76: ROSE GOLD
B77: ANGLE COCK WITH WF Rose Gold | C77: RGALAC101 | D77: CANVAS | E77: 3240 | F77: 0.05 | G77: 0.13 | H77: =F77*E77 -> 162 | I77: =G77*(E77+H77) -> 442.26 | J77: =E77+H77+I77 -> 3844.26 | K77: 0.2 | L77: =J77*K77 -> 768.852 | M77: =J77+L77 -> 4613.112 | N77: 0.2 | O77: =$M77/(1-N77) -> 5766.39 | P77: =MROUND(O77,10) -> 5770
B78: BIB COCK WITH WF Rose Gold | C78: RGALBC101 | D78: CANVAS | E78: 4520 | F78: 0.05 | G78: 0.13 | H78: =F78*E78 -> 226 | I78: =G78*(E78+H78) -> 616.98 | J78: =E78+H78+I78 -> 5362.98 | K78: 0.2 | L78: =J78*K78 -> 1072.596 | M78: =J78+L78 -> 6435.576 | N78: 0.2 | O78: =$M78/(1-N78) -> 8044.47 | P78: =MROUND(O78,10) -> 8040
B79: BIB COCK 2-IN-1 WITH WF Rose Gold | C79: RGALBC102 | D79: CANVAS | E79: 5900 | F79: 0.05 | G79: 0.13 | H79: =F79*E79 -> 295 | I79: =G79*(E79+H79) -> 805.35 | J79: =E79+H79+I79 -> 7000.35 | K79: 0.2 | L79: =J79*K79 -> 1400.07 | M79: =J79+L79 -> 8400.42 | N79: 0.2 | O79: =$M79/(1-N79) -> 10500.525 | P79: =MROUND(O79,10) -> 10500
B80: SLBM W/O PWS Rose Gold | C80: RGALBM101 | D80: CANVAS | E80: 10600 | F80: 0.05 | G80: 0.13 | H80: =F80*E80 -> 530 | I80: =G80*(E80+H80) -> 1446.9 | J80: =E80+H80+I80 -> 12576.9 | K80: 0.2 | L80: =J80*K80 -> 2515.38 | M80: =J80+L80 -> 15092.28 | N80: 0.2 | O80: =$M80/(1-N80) -> 18865.35 | P80: =MROUND(O80,10) -> 18870
B81: SLBM EXTENDED Rose Gold | C81: RGALBM102 | D81: CANVAS | E81: 13520 | F81: 0.05 | G81: 0.13 | H81: =F81*E81 -> 676 | I81: =G81*(E81+H81) -> 1845.48 | J81: =E81+H81+I81 -> 16041.48 | K81: 0.2 | L81: =J81*K81 -> 3208.296 | M81: =J81+L81 -> 19249.776 | N81: 0.2 | O81: =$M81/(1-N81) -> 24062.22 | P81: =MROUND(O81,10) -> 24060
B82: UPPER SLCD FOR BASIN SPOUT Rose Gold | C82: RGALDV103U | D82: CANVAS | E82: 9040 | F82: 0.05 | G82: 0.13 | H82: =F82*E82 -> 452 | I82: =G82*(E82+H82) -> 1233.96 | J82: =E82+H82+I82 -> 10725.96 | K82: 0.2 | L82: =J82*K82 -> 2145.192 | M82: =J82+L82 -> 12871.152 | N82: 0.2 | O82: =$M82/(1-N82) -> 16088.94 | P82: =MROUND(O82,10) -> 16090
B83: UPPER SLCD HF PUSH Rose Gold | C83: RGALDV111U | D83: CANVAS | E83: 4360 | F83: 0.05 | G83: 0.13 | H83: =F83*E83 -> 218 | I83: =G83*(E83+H83) -> 595.14 | J83: =E83+H83+I83 -> 5173.14 | K83: 0.2 | L83: =J83*K83 -> 1034.628 | M83: =J83+L83 -> 6207.768 | N83: 0.2 | O83: =$M83/(1-N83) -> 7759.71 | P83: =MROUND(O83,10) -> 7760
B84: BT PLAIN SPOUT Rose Gold | C84: RGALSP101 | D84: CANVAS | E84: 3640 | F84: 0.05 | G84: 0.13 | H84: =F84*E84 -> 182 | I84: =G84*(E84+H84) -> 496.86 | J84: =E84+H84+I84 -> 4318.86 | K84: 0.2 | L84: =J84*K84 -> 863.772 | M84: =J84+L84 -> 5182.632 | N84: 0.2 | O84: =$M84/(1-N84) -> 6478.29 | P84: =MROUND(O84,10) -> 6480
B85: BUTTON SPOUT Rose Gold | C85: RGALSP102 | D85: CANVAS | E85: 3880 | F85: 0.05 | G85: 0.13 | H85: =F85*E85 -> 194 | I85: =G85*(E85+H85) -> 529.62 | J85: =E85+H85+I85 -> 4603.62 | K85: 0.15 | L85: =J85*K85 -> 690.543 | M85: =J85+L85 -> 5294.163 | N85: 0.2 | O85: =$M85/(1-N85) -> 6617.7037 | P85: =MROUND(O85,10) -> 6620
B86: BODY SLCD B. SPOUT NEW (CASTED) Rose Gol | C86: RGB2BD101 | D86: CANVAS | E86: 7460 | F86: 0.05 | G86: 0.13 | H86: =F86*E86 -> 373 | I86: =G86*(E86+H86) -> 1018.29 | J86: =E86+H86+I86 -> 8851.29 | K86: 0.2 | L86: =J86*K86 -> 1770.258 | M86: =J86+L86 -> 10621.548 | N86: 0.2 | O86: =$M86/(1-N86) -> 13276.935 | P86: =MROUND(O86,10) -> 13280
B87: BODY ROYALE INSPIRE SLCD HF Rose Gold | C87: RGB2DV202 | D87: CANVAS | E87: 8900 | F87: 0.05 | G87: 0.13 | H87: =F87*E87 -> 445 | I87: =G87*(E87+H87) -> 1214.85 | J87: =E87+H87+I87 -> 10559.85 | K87: 0.2 | L87: =J87*K87 -> 2111.97 | M87: =J87+L87 -> 12671.82 | N87: 0.2 | O87: =$M87/(1-N87) -> 15839.775 | P87: =MROUND(O87,10) -> 15840
B88: 9 inch OHS Round Rose Gold | C88: RGBHRF101 | D88: CANVAS | E88: 8450 | F88: 0.05 | G88: 0.13 | H88: =F88*E88 -> 422.5 | I88: =G88*(E88+H88) -> 1153.425 | J88: =E88+H88+I88 -> 10025.925 | K88: 0.2 | L88: =J88*K88 -> 2005.185 | M88: =J88+L88 -> 12031.11 | N88: 0.2 | O88: =$M88/(1-N88) -> 15038.887 | P88: =MROUND(O88,10) -> 15040
... B101: 18" RFS arm round New Rose Gold | C101: RGSA107N | D101: CANVAS | E101: 4420 | F101: 0.05 | G101: 0.13 | H101: =F101*E101 -> 221 | I101: =G101*(E101+H101) -> 603.33 | J101: =E101+H101+I101 -> 5244.33 | K101: 0.2 | L101: =J101*K101 -> 1048.866 | M101: =J101+L101 -> 6293.196 | N101: 0.2 | O101: =$M101/(1-N101) -> 7866.495 | P101: =MROUND(O101,10) -> 7870
B102: BATHSENSE-SENSOR
B103: BS SENSOR AERATOR | C103: BSSE101 | D103: BATHSENSE-SENSOR | E103: 7740 | F103: 0.05 | G103: 0.13 | H103: =F103*E103 -> 387 | I103: =G103*(E103+H103) -> 1056.51 | J103: =E103+H103+I103 -> 9183.51 | K103: 0.15 | L103: =J103*K103 -> 1377.5265 | M103: =J103+L103 -> 10561.037 | N103: 0.2 | O103: =$M103/(1-N103) -> 13201.296 | P103: =MROUND(O103,10) -> 13200
B104: SENSOR FAUCET TABLE MOUNTED | C104: BSSF102 | D104: BATHSENSE-SENSOR | E104: 12350 | F104: 0.05 | G104: 0.13 | H104: =F104*E104 -> 617.5 | I104: =G104*(E104+H104) -> 1685.775 | J104: =E104+H104+I104 -> 14653.275 | K104: 0.15 | L104: =J104*K104 -> 2197.9913 | M104: =J104+L104 -> 16851.266 | N104: 0.2 | O104: =$M104/(1-N104) -> 21064.083 | P104: =MROUND(O104,10) -> 21060
B105: SENSOR FAUCET TABLE MOUNTED | C105: BSSF104 | D105: BATHSENSE-SENSOR | E105: 14980 | F105: 0.05 | G105: 0.13 | H105: =F105*E105 -> 749 | I105: =G105*(E105+H105) -> 2044.77 | J105: =E105+H105+I105 -> 17773.77 | K105: 0.15 | L105: =J105*K105 -> 2666.0655 | M105: =J105+L105 -> 20439.836 | N105: 0.2 | O105: =$M105/(1-N105) -> 25549.794 | P105: =MROUND(O105,10) -> 25550
B106: ROYALE-SENSORS
B107: SENSOR BASIN TAP RESF101 | C107: RESF101 | D107: ROYALE-SENSORS | E107: 11930 | F107: 0.05 | G107: 0.13 | H107: =F107*E107 -> 596.5 | I107: =G107*(E107+H107) -> 1628.445 | J107: =E107+H107+I107 -> 14154.945 | K107: 0.15 | L107: =J107*K107 -> 2123.2417 | M107: =J107+L107 -> 16278.187 | N107: 0.2 | O107: =$M107/(1-N107) -> 20347.733 | P107: =MROUND(O107,10) -> 20350
B108: SENSOR BASIN TAP RESF103 | C108: RESF103 | D108: ROYALE-SENSORS | E108: 16110 | F108: 0.05 | G108: 0.13 | H108: =F108*E108 -> 805.5 | I108: =G108*(E108+H108) -> 2199.015 | J108: =E108+H108+I108 -> 19114.515 | K108: 0.15 | L108: =J108*K108 -> 2867.1772 | M108: =J108+L108 -> 21981.692 | N108: 0.2 | O108: =$M108/(1-N108) -> 27477.115 | P108: =MROUND(O108,10) -> 27480
B109: AUTOCLOSE-TAP
B110: AUTO CLOSE PILLAR COCK | C110: ATC01 | D110: AUTOCLOSE TAP | E110: 3020 | F110: 0.05 | G110: 0.13 | H110: =F110*E110 -> 151 | I110: =G110*(E110+H110) -> 412.23 | J110: =E110+H110+I110 -> 3583.23 | K110: 0.15 | L110: =J110*K110 -> 537.4845 | M110: =J110+L110 -> 4120.7145 | N110: 0.2 | O110: =$M110/(1-N110) -> 5150.8931 | P110: =MROUND(O110,10) -> 5150
B111: AUTO CLOSE BIB COCK | C111: ATC02 | D111: AUTOCLOSE-TAP | E111: 2630 | F111: 0.05 | G111: 0.13 | H111: =F111*E111 -> 131.5 | I111: =G111*(E111+H111) -> 358.995 | J111: =E111+H111+I111 -> 3120.495 | K111: 0.15 | L111: =J111*K111 -> 468.07425 | M111: =J111+L111 -> 3588.5693 | N111: 0.2 | O111: =$M111/(1-N111) -> 4485.7116 | P111: =MROUND(O111,10) -> 4490
B112: URINAL BUTTON FLUSHER 1/2" | C112: ATC03 | D112: AUTOCLOSE-TAP | E112: 2810 | F112: 0.05 | G112: 0.13 | H112: =F112*E112 -> 140.5 | I112: =G112*(E112+H112) -> 383.565 | J112: =E112+H112+I112 -> 3334.065 | K112: 0.15 | L112: =J112*K112 -> 500.10975 | M112: =J112+L112 -> 3834.1748 | N112: 0.2 | O112: =$M112/(1-N112) -> 4792.7184 | P112: =MROUND(O112,10) -> 4790
B113: GOLD RUSH
B114: SLBM W/O PWS | C114: GRBM101 | D114: GOLD RUSH | E114: 29220 | F114: 0.05 | G114: 0.13 | H114: =F114*E114 -> 1461 | I114: =G114*(E114+H114) -> 3988.53 | J114: =E114+H114+I114 -> 34669.53 | K114: 0.15 | L114: =J114*K114 -> 5200.4295 | M114: =J114+L114 -> 39869.959 | N114: 0.2 | O114: =$M114/(1-N114) -> 49837.449 | P114: =MROUND(O114,10) -> 49840
B115: BODY GR SLCD HIGH FLOW | C115: GRDV202 | D115: GOLD RUSH | E115: 7970 | F115: 0.05 | G115: 0.13 | H115: =F115*E115 -> 398.5 | I115: =G115*(E115+H115) -> 1087.905 | J115: =E115+H115+I115 -> 9456.405 | K115: 0.15 | L115: =J115*K115 -> 1418.4607 | M115: =J115+L115 -> 10874.866 | N115: 0.2 | O115: =$M115/(1-N115) -> 13593.582 | P115: =MROUND(O115,10) -> 13590
B116: UPPER GR SLCD | C116: GRDV202U | D116: GOLD RUSH | E116: 20400 | F116: 0.05 | G116: 0.13 | H116: =F116*E116 -> 1020 | I116: =G116*(E116+H116) -> 2784.6 | J116: =E116+H116+I116 -> 24204.6 | K116: 0.15 | L116: =J116*K116 -> 3630.69 | M116: =J116+L116 -> 27835.29 | N116: 0.2 | O116: =$M116/(1-N116) -> 34794.112 | P116: =MROUND(O116,10) -> 34790
B117: GR PLAIN BATH SPT | C117: GRSP101 | D117: GOLD RUSH | E117: 10270 | F117: 0.05 | G117: 0.13 | H117: =F117*E117 -> 513.5 | I117: =G117*(E117+H117) -> 1401.855 | J117: =E117+H117+I117 -> 12185.355 | K117: 0.15 | L117: =J117*K117 -> 1827.8032 | M117: =J117+L117 -> 14013.158 | N117: 0.2 | O117: =$M117/(1-N117) -> 17516.448 | P117: =MROUND(O117,10) -> 17520
B118: GR BUTTON SPOUT | C118: GRSP102 | D118: GOLD RUSH | E118: 11750 | F118: 0.05 | G118: 0.13 | H118: =F118*E118 -> 587.5 | I118: =G118*(E118+H118) -> 1603.875 | J118: =E118+H118+I118 -> 13941.375 | K118: 0.15 | L118: =J118*K118 -> 2091.2062 | M118: =J118+L118 -> 16032.581 | N118: 0.2 | O118: =$M118/(1-N118) -> 20040.727 | P118: =MROUND(O118,10) -> 20040
B119: SLWM WITH TSA ONLY | C119: GRWM203 | D119: GOLD RUSH | E119: 34820 | F119: 0.05 | G119: 0.13 | H119: =F119*E119 -> 1741 | I119: =G119*(E119+H119) -> 4752.93 | J119: =E119+H119+I119 -> 41313.93 | K119: 0.15 | L119: =J119*K119 -> 6197.0895 | M119: =J119+L119 -> 47511.02 | N119: 0.2 | O119: =$M119/(1-N119) -> 59388.774 | P119: =MROUND(O119,10) -> 59390
B120: ROYALE ROUND AC GDFL | C120: REAC701 | D120: GOLD RUSH | E120: 2200 | F120: 0.05 | G120: 0.13 | H120: =F120*E120 -> 110 | I120: =G120*(E120+H120) -> 300.3 | J120: =E120+H120+I120 -> 2610.3 | K120: 0.15 | L120: =J120*K120 -> 391.545 | M120: =J120+L120 -> 3001.845 | N120: 0.2 | O120: =$M120/(1-N120) -> 3752.3063 | P120: =MROUND(O120,10) -> 3750
B121: 9 INCH SQUARE GOLD CLR SHOWER | C121: RSRF702 | D121: GOLD RUSH | E121: 13220 | F121: 0.05 | G121: 0.13 | H121: =F121*E121 -> 661 | I121: =G121*(E121+H121) -> 1804.53 | J121: =E121+H121+I121 -> 15685.53 | K121: 0.15 | L121: =J121*K121 -> 2352.8295 | M121: =J121+L121 -> 18038.359 | N121: 0.2 | O121: =$M121/(1-N121) -> 22547.949 | P121: =MROUND(O121,10) -> 22550
B122: 15'' RFS ARM ROUND GOLD | C122: RSSA715 | D122: GOLD RUSH | E122: 2530 | F122: 0.05 | G122: 0.13 | H122: =F122*E122 -> 126.5 | I122: =G122*(E122+H122) -> 345.345 | J122: =E122+H122+I122 -> 3001.845 | K122: 0.15 | L122: =J122*K122 -> 450.27675 | M122: =J122+L122 -> 3452.1218 | N122: 0.2 | O122: =$M122/(1-N122) -> 4315.1522 | P122: =MROUND(O122,10) -> 4320
B123: 5 INCH WHITE GOLD HAND SHOWER | C123: RSTS202 | D123: GOLD RUSH | E123: 8870 | F123: 0.05 | G123: 0.13 | H123: =F123*E123 -> 443.5 | I123: =G123*(E123+H123) -> 1210.755 | J123: =E123+H123+I123 -> 10524.255 | K123: 0.15 | L123: =J123*K123 -> 1578.6383 | M123: =J123+L123 -> 12102.893 | N123: 0.2 | O123: =$M123/(1-N123) -> 15128.617 | P123: =MROUND(O123,10) -> 15130
B124: PEARL GLORY
B125: PG BIB COCK 2-IN-1 | C125: PGBC102 | D125: PEARL GLORY | E125: 9780 | F125: 0.05 | G125: 0.13 | H125: =F125*E125 -> 489 | I125: =G125*(E125+H125) -> 1334.97 | J125: =E125+H125+I125 -> 11603.97 | K125: 0.15 | L125: =J125*K125 -> 1740.5955 | M125: =J125+L125 -> 13344.565 | N125: 0.2 | O125: =$M125/(1-N125) -> 16680.707 | P125: =MROUND(O125,10) -> 16680
B126: SLBM W/O PWS | C126: PGBM101 | D126: PEARL GLORY | E126: 21570 | F126: 0.05 | G126: 0.13 | H126: =F126*E126 -> 1078.5 | I126: =G126*(E126+H126) -> 2944.305 | J126: =E126+H126+I126 -> 25592.805 | K126: 0.15 | L126: =J126*K126 -> 3838.9207 | M126: =J126+L126 -> 29431.726 | N126: 0.2 | O126: =$M126/(1-N126) -> 36789.657 | P126: =MROUND(O126,10) -> 36790
B127: SLCD for Basin Spout | C127: PGDV101 | D127: PEARL GLORY | E127: 23590 | F127: 0.05 | G127: 0.13 | H127: =F127*E127 -> 1179.5 | I127: =G127*(E127+H127) -> 3220.035 | J127: =E127+H127+I127 -> 27989.535 | K127: 0.15 | L127: =J127*K127 -> 4198.4302 | M127: =J127+L127 -> 32187.965 | N127: 0.2 | O127: =$M127/(1-N127) -> 40234.957 | P127: =MROUND(O127,10) -> 40230
B128: BODY PG SS SLCD HIGH FLOW | C128: PGDV202 | D128: PEARL GLORY | E128: 7080 | F128: 0.05 | G128: 0.13 | H128: =F128*E128 -> 354 | I128: =G128*(E128+H128) -> 966.42 | J128: =E128+H128+I128 -> 8400.42 | K128: 0.15 | L128: =J128*K128 -> 1260.063 | M128: =J128+L128 -> 9660.483 | N128: 0.2 | O128: =$M128/(1-N128) -> 12075.604 | P128: =MROUND(O128,10) -> 12080
B129: UPPER PG SLCD | C129: PGDV202U | D129: PEARL GLORY | E129: 19950 | F129: 0.05 | G129: 0.13 | H129: =F129*E129 -> 997.5 | I129: =G129*(E129+H129) -> 2723.175 | J129: =E129+H129+I129 -> 23670.675 | K129: 0.15 | L129: =J129*K129 -> 3550.6012 | M129: =J129+L129 -> 27221.276 | N129: 0.2 | O129: =$M129/(1-N129) -> 34026.595 | P129: =MROUND(O129,10) -> 34030
B130: SL SINK MIXER TM | C130: PGSM401 | D130: PEARL GLORY | E130: 23590 | F130: 0.05 | G130: 0.13 | H130: =F130*E130 -> 1179.5 | I130: =G130*(E130+H130) -> 3220.035 | J130: =E130+H130+I130 -> 27989.535 | K130: 0.15 | L130: =J130*K130 -> 4198.4302 | M130: =J130+L130 -> 32187.965 | N130: 0.2 | O130: =$M130/(1-N130) -> 40234.957 | P130: =MROUND(O130,10) -> 40230
B131: PG PLAIN BATH SPT | C131: PGSP101 | D131: PEARL GLORY | E131: 9780 | F131: 0.05 | G131: 0.13 | H131: =F131*E131 -> 489 | I131: =G131*(E131+H131) -> 1334.97 | J131: =E131+H131+I131 -> 11603.97 | K131: 0.15 | L131: =J131*K131 -> 1740.5955 | M131: =J131+L131 -> 13344.565 | N131: 0.2 | O131: =$M131/(1-N131) -> 16680.707 | P131: =MROUND(O131,10) -> 16680
B132: PG BUTTON SPOUT | C132: PGSP102 | D132: PEARL GLORY | E132: 10990 | F132: 0.05 | G132: 0.13 | H132: =F132*E132 -> 549.5 | I132: =G132*(E132+H132) -> 1500.135 | J132: =E132+H132+I132 -> 13039.635 | K132: 0.15 | L132: =J132*K132 -> 1955.9452 | M132: =J132+L132 -> 14995.58 | N132: 0.2 | O132: =$M132/(1-N132) -> 18744.475 | P132: =MROUND(O132,10) -> 18740
B133: SLWM WITH TSA ONLY | C133: PGWM203 | D133: PEARL GLORY | E133: 32360 | F133: 0.05 | G133: 0.13 | H133: =F133*E133 -> 1618 | I133: =G133*(E133+H133) -> 4417.14 | J133: =E133+H133+I133 -> 38395.14 | K133: 0.15 | L133: =J133*K133 -> 5759.271 | M133: =J133+L133 -> 44154.411 | N133: 0.2 | O133: =$M133/(1-N133) -> 55193.014 | P133: =MROUND(O133,10) -> 55190
B134: DIMANTA
B135: DI BIB COCK 2-IN-1 | C135: DIBC102 | D135: DIMANTA | E135: 9370 | F135: 0.05 | G135: 0.13 | H135: =F135*E135 -> 468.5 | I135: =G135*(E135+H135) -> 1279.005 | J135: =E135+H135+I135 -> 11117.505 | K135: 0.15 | L135: =J135*K135 -> 1667.6258 | M135: =J135+L135 -> 12785.131 | N135: 0.2 | O135: =$M135/(1-N135) -> 15981.413 | P135: =MROUND(O135,10) -> 15980
B136: SLBM W/O PWS | C136: DIBM101 | D136: DIMANTA | E136: 17330 | F136: 0.05 | G136: 0.13 | H136: =F136*E136 -> 866.5 | I136: =G136*(E136+H136) -> 2365.545 | J136: =E136+H136+I136 -> 20562.045 | K136: 0.15 | L136: =J136*K136 -> 3084.3067 | M136: =J136+L136 -> 23646.352 | N136: 0.2 | O136: =$M136/(1-N136) -> 29557.94 | P136: =MROUND(O136,10) -> 29560
B137: SLCD for Basin Spout | C137: DIDV101 | D137: DIMANTA | E137: 20560 | F137: 0.05 | G137: 0.13 | H137: =F137*E137 -> 1028 | I137: =G137*(E137+H137) -> 2806.44 | J137: =E137+H137+I137 -> 24394.44 | K137: 0.15 | L137: =J137*K137 -> 3659.166 | M137: =J137+L137 -> 28053.606 | N137: 0.2 | O137: =$M137/(1-N137) -> 35067.007 | P137: =MROUND(O137,10) -> 35070
B138: BODY DI SLCD HIGH FLOW | C138: DIDV202 | D138: DIMANTA | E138: 6210 | F138: 0.05 | G138: 0.13 | H138: =F138*E138 -> 310.5 | I138: =G138*(E138+H138) -> 847.665 | J138: =E138+H138+I138 -> 7368.165 | K138: 0.15 | L138: =J138*K138 -> 1105.2247 | M138: =J138+L138 -> 8473.3898 | N138: 0.2 | O138: =$M138/(1-N138) -> 10591.737 | P138: =MROUND(O138,10) -> 10590
B139: UPPER DI SLCD | C139: DIDV202U | D139: DIMANTA | E139: 20220 | F139: 0.05 | G139: 0.13 | H139: =F139*E139 -> 1011 | I139: =G139*(E139+H139) -> 2760.03 | J139: =E139+H139+I139 -> 23991.03 | K139: 0.15 | L139: =J139*K139 -> 3598.6545 | M139: =J139+L139 -> 27589.684 | N139: 0.2 | O139: =$M139/(1-N139) -> 34487.106 | P139: =MROUND(O139,10) -> 34490
B140: SL SINK MIXER TM | C140: DISM401 | D140: DIMANTA | E140: 20220 | F140: 0.05 | G140: 0.13 | H140: =F140*E140 -> 1011 | I140: =G140*(E140+H140) -> 2760.03 | J140: =E140+H140+I140 -> 23991.03 | K140: 0.15 | L140: =J140*K140 -> 3598.6545 | M140: =J140+L140 -> 27589.684 | N140: 0.2 | O140: =$M140/(1-N140) -> 34487.106 | P140: =MROUND(O140,10) -> 34490
B141: DI PLAIN BATH SPT | C141: DISP101 | D141: DIMANTA | E141: 9640 | F141: 0.05 | G141: 0.13 | H141: =F141*E141 -> 482 | I141: =G141*(E141+H141) -> 1315.86 | J141: =E141+H141+I141 -> 11437.86 | K141: 0.15 | L141: =J141*K141 -> 1715.679 | M141: =J141+L141 -> 13153.539 | N141: 0.2 | O141: =$M141/(1-N141) -> 16441.924 | P141: =MROUND(O141,10) -> 16440
B142: SLWM WITH TSA ONLY | C142: DIWM203 | D142: DIMANTA | E142: 24810 | F142: 0.05 | G142: 0.13 | H142: =F142*E142 -> 1240.5 | I142: =G142*(E142+H142) -> 3386.565 | J142: =E142+H142+I142 -> 29437.065 | K142: 0.15 | L142: =J142*K142 -> 4415.5597 | M142: =J142+L142 -> 33852.625 | N142: 0.2 | O142: =$M142/(1-N142) -> 42315.781 | P142: =MROUND(O142,10) -> 42320
B143: MANHATTAN
...

Sheet Sheet7
B1: 9990
B2: 2540

Sheet Sheet5

Sheet Sheet8

Sheet Sheet6

Sheet binaya
E2: 9990

Sheet Painter
A1: Painter | B1: Mobile | J1: Sanjib Shrestha | K1: 9861024765
A2: Basudev Chapagain | B2: 9841511785 | J2: Shiva Bhandari | K2: 9741470293
A3: Bharat Chaurasiya | B3: 9841786637 | J3: Khadga Pd. Tamang | K3: 9841907498
A4: MD Anzauul | B4: 9803575598 | J4: Alok Ghorasaini | K4: 9841471526
A5: Mr. Yuvaraj Lungele | B5: 9841433416 | J5: Bohoj Bd Shrestha | K5: 9851058830
A6: Maila Tamang | B6: 9841834335 | J6: Bhupendra Raj Giri | K6: 9841365614
A7: Sandip Sharma | B7: 9845915826 | J7: Chettra bahadur Thapa Magar | K7: 9860813213
A8: Ram Bahadur Rai | B8: 9840125584 | J8: Santosh kumar singh | K8: 9841219496
A9: Sanjib Shrestha | B9: 9861024765 | J9: Surendra Hada | K9: 9843141045
A10: Shiva Bhandari | B10: 9741470293 | J10: Santosh KC | K10: 9851063076
A11: Bal Bahadur lamichhane | B11: 9843907066 | J11: Bhoj Bdr Shrestha | K11: 9808346072
A12: Bola Singh | B12: 9841828757 | J12: Umesh payakurel | K12: 9851089876
A13: Hiralal Prasad Gupta | B13: 9841010503
A14: Khadga Pd. Tamang | B14: 9841907498
A15: Kishna Bahadur Baruwal | B15: 9860997691
A16: Lila Pd Sapkota | B16: 9841935380
A17: Man Bdr Bhattarai | B17: 9818701617
A18: Raj Kumar Bhandari | B18: 9841371752
A19: Tej Narayan Chaudhary | B19: 9803800176
A20: Alok Ghorasaini | B20: 9841471526
A21: Bohoj Bd Shrestha | B21: 9851058830
A22: Sonu Maharjan | B22: 9841723121
A23: Krishna Bdr Rai | B23: 9803169614
A24: Sworup Lamichhane | B24: 9851187993
... A54: Thal Bahadur Thapa Magar | B54: 9813028209

Sheet Nala Stock 05-09
A1: HQ13 04 | C1: 4LTR | D1: 3
A2: HQ10 04 | C2: 4LTR | D2: 3
A3: HQ20 04 | C3: 4LTR | D3: 2
A4: PS10 04 | C4: 4LTR | D4: 1
A5: RB22 04 | C5: 4LTR | D5: 1
A6: BW01 04 | C6: 4LTR | D6: 3
A7: PS01 04 | C7: 4LTR | D7: 1
A8: AB02 04 | C8: 4LTR | D8: 1
A9: RB22 04 | C9: 4LTR | D9: 4
A10: RB10 04 | C10: 4LTR | D10: 7
A11: TE20 04 | C11: 4LTR | D11: 4
A12: RB01 04 | C12: 4LTR | D12: 3
... A205: DR.FIXIT FEVIMATE T.L. WHITE 0.5 | C205: 0.5KG | D205: 4

Sheet Sheet9
B2: 9990
B3: 2540

Sheet Sheet10

Sheet Sheet11

Sheet Sheet12

Sheet Sheet13

Sheet Sheet14

Sheet Sheet15

Sheet Sheet16

Sheet Sheet17

Sheet Sheet18

Sheet Sheet19

Sheet Sheet20

Sheet Sheet21

Sheet Sheet22

Sheet Sheet23

Sheet Sheet24
